{
  "timestamp": "2025-10-23T17:08:39.037989",
  "concerts": [
    {
      "artist": "London Symphony Orchestra",
      "name": "Thunder Bay Symphony Orchestra-The Road To London (Masterworks #2)",
      "venue": "Thunder Bay Community Auditorium",
      "city": "Thunder Bay",
      "country": "Canada",
      "country_code": "CA",
      "date": "2025-11-28",
      "time": "19:30:00",
      "url": "https://www.ticketmaster.ca/thunder-bay-symphony-orchestrathe-road-to-thunder-bay-ontario-11-28-2025/event/100062F8B47B2752",
      "source": "Ticketmaster",
      "id": "177ZvxG62xVrwq3"
    }
  ]
}