{
  "timestamp": "2025-10-23T17:11:55.387604",
  "concerts": [
    {
      "artist": "Big Thief",
      "name": "Big Thief - Somersault Slide 360 Tour",
      "venue": "The Anthem",
      "city": "Washington",
      "country": "United States Of America",
      "country_code": "US",
      "date": "2025-10-24",
      "time": "20:00:00",
      "url": "https://www.ticketmaster.com/big-thief-somersault-slide-360-tour-washington-district-of-columbia-10-24-2025/event/150062A1BAC14DE8",
      "source": "Ticketmaster",
      "id": "17A8vxG61kBYfMI"
    },
    {
      "artist": "Big Thief",
      "name": "Big Thief",
      "venue": "Forest Hills Stadium",
      "city": "Forest Hills",
      "country": "United States Of America",
      "country_code": "US",
      "date": "2025-10-25",
      "time": "19:00:00",
      "url": "https://www.ticketmaster.com/event/Z7r9jZ1A74YPp",
      "source": "Ticketmaster",
      "id": "Z7r9jZ1A74YPp"
    },
    {
      "artist": "Big Thief",
      "name": "Big Thief",
      "venue": "Red Hat Amphitheater",
      "city": "Raleigh",
      "country": "United States Of America",
      "country_code": "US",
      "date": "2025-10-29",
      "time": "19:00:00",
      "url": "https://www.ticketmaster.com/big-thief-raleigh-north-carolina-10-29-2025/event/2D00629E12CC8852",
      "source": "Ticketmaster",
      "id": "G5eVZbtz3SF-3"
    },
    {
      "artist": "Big Thief",
      "name": "Big Thief",
      "venue": "Fox Theatre - Atlanta",
      "city": "Atlanta",
      "country": "United States Of America",
      "country_code": "US",
      "date": "2025-10-30",
      "time": "20:00:00",
      "url": "https://www.ticketmaster.com/event/Z7r9jZ1A7bdq8",
      "source": "Ticketmaster",
      "id": "Z7r9jZ1A7bdq8"
    },
    {
      "artist": "Big Thief",
      "name": "Big Thief",
      "venue": "Saenger Theatre-New Orleans",
      "city": "New Orleans",
      "country": "United States Of America",
      "country_code": "US",
      "date": "2025-10-31",
      "time": "20:00:00",
      "url": "https://www.ticketmaster.com/event/Z7r9jZ1A7p4x9",
      "source": "Ticketmaster",
      "id": "Z7r9jZ1A7p4x9"
    },
    {
      "artist": "Big Thief",
      "name": "Big Thief",
      "venue": "Cain's Ballroom",
      "city": "Tulsa",
      "country": "United States Of America",
      "country_code": "US",
      "date": "2025-11-03",
      "time": "19:30:00",
      "url": "https://www.ticketmaster.com/event/Z7r9jZ1A7pk0y",
      "source": "Ticketmaster",
      "id": "Z7r9jZ1A7pk0y"
    },
    {
      "artist": "Big Thief",
      "name": "Big Thief",
      "venue": "The Bomb Factory",
      "city": "Dallas",
      "country": "United States Of America",
      "country_code": "US",
      "date": "2025-11-04",
      "time": "20:00:00",
      "url": "https://www.ticketmaster.com/event/Z7r9jZ1A7p9C3",
      "source": "Ticketmaster",
      "id": "Z7r9jZ1A7p9C3"
    },
    {
      "artist": "Big Thief",
      "name": "Big Thief: Somersault Slide 360 Tour",
      "venue": "Moody Amphitheater",
      "city": "Austin",
      "country": "United States Of America",
      "country_code": "US",
      "date": "2025-11-05",
      "time": "19:00:00",
      "url": "https://www.ticketmaster.com/big-thief-somersault-slide-360-tour-austin-texas-11-05-2025/event/3A0062A3F7E770E0",
      "source": "Ticketmaster",
      "id": "G5dIZbn2MyMdO"
    },
    {
      "artist": "Big Thief",
      "name": "Big Thief - Somersault Slide 360 Tour",
      "venue": "White Oak Music Hall Lawn",
      "city": "Houston",
      "country": "United States Of America",
      "country_code": "US",
      "date": "2025-11-07",
      "time": "18:00:00",
      "url": "https://www.ticketmaster.com/big-thief-somersault-slide-360-tour-houston-texas-11-07-2025/event/3A00629E7FA11AE4",
      "source": "Ticketmaster",
      "id": "G5dIZbtyTIol0"
    },
    {
      "artist": "Big Thief",
      "name": "Big Thief – Somersault Slide 360 Tour 2026",
      "venue": "Unknown venue",
      "city": "Amsterdam",
      "country": "Netherlands",
      "country_code": "NL",
      "date": "2026-04-21",
      "time": "20:00:00",
      "url": "https://www.ticketmaster.nl/event/big-thief--somersault-slide-360-tour-2026-tickets/1048333779?language=en-us",
      "source": "Ticketmaster",
      "id": "Z698xZbpZ16vvFGSqy"
    },
    {
      "artist": "Big Thief",
      "name": "Big Thief | Comfort Seats",
      "venue": "AFAS Live Loge",
      "city": "Amsterdam",
      "country": "Netherlands",
      "country_code": "NL",
      "date": "2026-04-21",
      "time": "20:00:00",
      "url": "https://www.ticketmaster.nl/event/big-thief-%7C-comfort-seats-tickets/614445708?language=en-us",
      "source": "Ticketmaster",
      "id": "Z698xZbpZ1kbfoAjF"
    },
    {
      "artist": "Big Thief",
      "name": "Big Thief",
      "venue": "O2 Academy Brixton",
      "city": "London",
      "country": "Great Britain",
      "country_code": "GB",
      "date": "2026-04-23",
      "time": "19:00:00",
      "url": "https://www.ticketmaster.co.uk/big-thief-london-23-04-2026/event/3E00630BC57118CC",
      "source": "Ticketmaster",
      "id": "G5dzZbYRAjoNG"
    },
    {
      "artist": "Big Thief",
      "name": "Big Thief",
      "venue": "O2 Academy Brixton",
      "city": "London",
      "country": "Great Britain",
      "country_code": "GB",
      "date": "2026-04-24",
      "time": "19:00:00",
      "url": "https://www.ticketmaster.co.uk/big-thief-london-24-04-2026/event/3E00630BDC0C1AB2",
      "source": "Ticketmaster",
      "id": "G5dzZbYRjdvnw"
    },
    {
      "artist": "Big Thief",
      "name": "Big Thief",
      "venue": "O2 Academy Brixton",
      "city": "London",
      "country": "Great Britain",
      "country_code": "GB",
      "date": "2026-04-25",
      "time": "19:00:00",
      "url": "https://www.ticketmaster.co.uk/big-thief-london-25-04-2026/event/3E00630BDFAD1B35",
      "source": "Ticketmaster",
      "id": "G5dzZbYRLloig"
    },
    {
      "artist": "Big Thief",
      "name": "Big Thief",
      "venue": "O2 Academy Brixton",
      "city": "London",
      "country": "Great Britain",
      "country_code": "GB",
      "date": "2026-04-26",
      "time": "19:00:00",
      "url": "https://www.ticketmaster.co.uk/big-thief-london-26-04-2026/event/3E006329A0050BAB",
      "source": "Ticketmaster",
      "id": "G5dzZbwJOv8ml"
    },
    {
      "artist": "Big Thief",
      "name": "Big Thief",
      "venue": "3Arena",
      "city": "Dublin",
      "country": "Ireland",
      "country_code": "IE",
      "date": "2026-04-29",
      "time": "18:30:00",
      "url": "https://www.ticketmaster.ie/big-thief-dublin-29-04-2026/event/1800631581826F5D",
      "source": "Ticketmaster",
      "id": "1avOZbspvOJZd8kC"
    },
    {
      "artist": "Big Thief",
      "name": "Big Thief",
      "venue": "3Arena",
      "city": "Dublin",
      "country": "Irl",
      "country_code": "IRL",
      "date": "2026-04-29",
      "time": "18:30:00",
      "url": "",
      "source": "Ticketmaster",
      "id": "Za5ju3rKuqZDeYLbrP7GcC5n98PIn3BpFh"
    },
    {
      "artist": "Big Thief",
      "name": "Big Thief",
      "venue": "3Arena",
      "city": "Dublin",
      "country": "Irl",
      "country_code": "IRL",
      "date": "2026-04-29",
      "time": "18:30:00",
      "url": "",
      "source": "Ticketmaster",
      "id": "Za5ju3rKuqZDvuCPOO5gcuZ5Gl-S1yeaWc"
    },
    {
      "artist": "Big Thief",
      "name": "Big Thief",
      "venue": "Aviva Studios - Warehouse",
      "city": "Manchester",
      "country": "Great Britain",
      "country_code": "GB",
      "date": "2026-05-27",
      "time": "18:00:00",
      "url": "https://www.ticketweb.uk/event/big-thief-aviva-studios-warehouse-tickets/13951144?REFERRAL_ID=tmfeed",
      "source": "Ticketmaster",
      "id": "1AdFZbYGkUMJs2X"
    },
    {
      "artist": "Big Thief",
      "name": "Big Thief",
      "venue": "Aviva Studios - Warehouse",
      "city": "Manchester",
      "country": "Great Britain",
      "country_code": "GB",
      "date": "2026-05-28",
      "time": "18:00:00",
      "url": "https://www.ticketweb.uk/event/big-thief-aviva-studios-warehouse-tickets/13951154?REFERRAL_ID=tmfeed",
      "source": "Ticketmaster",
      "id": "1AdFZbYGkUzlv8X"
    },
    {
      "artist": "Big Thief",
      "name": "Big Thief: SOMERSAULT SLIDE 360",
      "venue": "Vorst Nationaal/Forest National",
      "city": "Forest (Brussels)",
      "country": "Belgium",
      "country_code": "BE",
      "date": "2026-06-02",
      "time": "18:30:00",
      "url": "https://www.ticketmaster.be/event/big-thief-somersault-slide-360-tickets/1161988483",
      "source": "Ticketmaster",
      "id": "Z698xZG2Z16vA-JF3d"
    }
  ]
}