{
  "timestamp": "2025-10-23T17:14:04.493794",
  "concerts": [
    {
      "artist": "Dead Sound",
      "name": "The Rock and Roll Playhouse: Sounds of Grateful Dead",
      "venue": "Galuppi's",
      "city": "Pompano Beach",
      "country": "United States Of America",
      "country_code": "US",
      "date": "2025-11-23",
      "time": "12:00:00",
      "url": "https://www.ticketmaster.com/the-rock-and-roll-playhouse-sounds-pompano-beach-florida-11-23-2025/event/0D00630F90291AC4",
      "source": "Ticketmaster",
      "id": "vvG1VZbYX81ol7"
    }
  ]
}