{
  "timestamp": "2025-10-23T17:07:33.313158",
  "concerts": [
    {
      "artist": "Melvins",
      "name": "Melvin Seals & JGB 2-Night Pass (10/23 and 10/24) (21+ Event)",
      "venue": "Ardmore Music Hall",
      "city": "Ardmore",
      "country": "United States Of America",
      "country_code": "US",
      "date": "2025-10-23",
      "time": "",
      "url": "https://www.ticketmaster.com/event/Z7r9jZ1A74xvb",
      "source": "Ticketmaster",
      "id": "Z7r9jZ1A74xvb"
    },
    {
      "artist": "Melvins",
      "name": "Melvin Seals & JGB Night 1 (21+ Event)",
      "venue": "Ardmore Music Hall",
      "city": "Ardmore",
      "country": "United States Of America",
      "country_code": "US",
      "date": "2025-10-23",
      "time": "20:00:00",
      "url": "https://www.ticketmaster.com/event/Z7r9jZ1A74xv9",
      "source": "Ticketmaster",
      "id": "Z7r9jZ1A74xv9"
    },
    {
      "artist": "Melvins",
      "name": "Melvin Seals & JGB Night 2 (21+ Event)",
      "venue": "Ardmore Music Hall",
      "city": "Ardmore",
      "country": "United States Of America",
      "country_code": "US",
      "date": "2025-10-24",
      "time": "20:00:00",
      "url": "https://www.ticketmaster.com/event/Z7r9jZ1A74xv_",
      "source": "Ticketmaster",
      "id": "Z7r9jZ1A74xv_"
    },
    {
      "artist": "Melvins",
      "name": "Melvin Seals and JGB (Guests Under 18 Require Accompanying Adult)",
      "venue": "Aggie Theater",
      "city": "Fort Collins",
      "country": "United States Of America",
      "country_code": "US",
      "date": "2025-10-30",
      "time": "20:00:00",
      "url": "https://www.ticketmaster.com/event/Z7r9jZ1A7bx-9",
      "source": "Ticketmaster",
      "id": "Z7r9jZ1A7bx-9"
    },
    {
      "artist": "Melvins",
      "name": "Melvin Seals and JGB, Night 1 - All Ages (under 16 with adult)",
      "venue": "Boulder Theater",
      "city": "Boulder",
      "country": "United States Of America",
      "country_code": "US",
      "date": "2025-10-31",
      "time": "20:00:00",
      "url": "https://www.ticketmaster.com/event/Z7r9jZ1A7bx-p",
      "source": "Ticketmaster",
      "id": "Z7r9jZ1A7bx-p"
    },
    {
      "artist": "Melvins",
      "name": "Melvin Seals and JGB: Night 2 - All Ages (under 16 with adult)",
      "venue": "Boulder Theater",
      "city": "Boulder",
      "country": "United States Of America",
      "country_code": "US",
      "date": "2025-11-01",
      "time": "20:00:00",
      "url": "https://www.ticketmaster.com/event/Z7r9jZ1A7bx-b",
      "source": "Ticketmaster",
      "id": "Z7r9jZ1A7bx-b"
    },
    {
      "artist": "Melvins",
      "name": "Tye Tribbett: We Outside Tour",
      "venue": "The Venue at Horseshoe Casino",
      "city": "Hammond",
      "country": "United States Of America",
      "country_code": "US",
      "date": "2025-11-08",
      "time": "20:00:00",
      "url": "https://www.ticketmaster.com/tye-tribbett-we-outside-tour-hammond-indiana-11-08-2025/event/070062FEA5302D4E",
      "source": "Ticketmaster",
      "id": "vvG1jZbRBPGegC"
    },
    {
      "artist": "Melvins",
      "name": "Melvin Seals and JGB",
      "venue": "The Guild Theatre - CA",
      "city": "Menlo Park",
      "country": "United States Of America",
      "country_code": "US",
      "date": "2025-11-14",
      "time": "20:00:00",
      "url": "https://www.ticketmaster.com/event/Z7r9jZ1A7j8_N",
      "source": "Ticketmaster",
      "id": "Z7r9jZ1A7j8_N"
    },
    {
      "artist": "Melvins",
      "name": "Melvin Seals and JGB",
      "venue": "The Guild Theatre - CA",
      "city": "Menlo Park",
      "country": "United States Of America",
      "country_code": "US",
      "date": "2025-11-15",
      "time": "20:00:00",
      "url": "https://www.ticketmaster.com/event/Z7r9jZ1A7j8_0",
      "source": "Ticketmaster",
      "id": "Z7r9jZ1A7j8_0"
    },
    {
      "artist": "Melvins",
      "name": "Tye Tribbett: We Outside Tour",
      "venue": "The Pavilion at Toyota Music Factory",
      "city": "Irving",
      "country": "United States Of America",
      "country_code": "US",
      "date": "2025-11-21",
      "time": "20:00:00",
      "url": "https://www.ticketmaster.com/tye-tribbett-we-outside-tour-irving-texas-11-21-2025/event/0C0062FEDB942DE8",
      "source": "Ticketmaster",
      "id": "vvG1YZbRDhPeMI"
    },
    {
      "artist": "Melvins",
      "name": "Melvin Seals & JGB",
      "venue": "Uptown Theatre Napa",
      "city": "Napa",
      "country": "United States Of America",
      "country_code": "US",
      "date": "2025-11-21",
      "time": "20:00:00",
      "url": "https://www.ticketmaster.com/melvin-seals-jgb-napa-california-11-21-2025/event/1C0062FF87C12825",
      "source": "Ticketmaster",
      "id": "G5vYZbRX6Y3OP"
    },
    {
      "artist": "Melvins",
      "name": "Melvin Funkenstein's",
      "venue": "Tipitina's",
      "city": "New Orleans",
      "country": "United States Of America",
      "country_code": "US",
      "date": "2025-12-14",
      "time": "20:00:00",
      "url": "https://www.ticketweb.com/event/melvin-funkensteins-tipitinas-tickets/14521733",
      "source": "Ticketmaster",
      "id": "rZ7HnEZ1Aff-jS"
    },
    {
      "artist": "Melvins",
      "name": "Melvin Seals w/ JGB",
      "venue": "The Cabot",
      "city": "Beverly",
      "country": "United States Of America",
      "country_code": "US",
      "date": "2026-02-27",
      "time": "19:00:00",
      "url": "https://www.ticketmaster.com/event/Z7r9jZ1A7jyqY",
      "source": "Ticketmaster",
      "id": "Z7r9jZ1A7jyqY"
    },
    {
      "artist": "Melvins",
      "name": "Sick New World",
      "venue": "Las Vegas Festival Grounds",
      "city": "Las Vegas",
      "country": "United States Of America",
      "country_code": "US",
      "date": "2026-04-25",
      "time": "11:00:00",
      "url": "https://on.fgtix.com/trk/H1KT",
      "source": "Ticketmaster",
      "id": "G5ezZbgp0VYB1"
    },
    {
      "artist": "Melvins",
      "name": "Sick New World Texas",
      "venue": "Texas Motor Speedway",
      "city": "Fort Worth",
      "country": "United States Of America",
      "country_code": "US",
      "date": "2026-10-24",
      "time": "12:00:00",
      "url": "https://on.fgtix.com/trk/nzwec",
      "source": "Ticketmaster",
      "id": "vvG1YZbgQetoBB"
    }
  ]
}