{
  "timestamp": "2025-10-23T17:12:42.727784",
  "concerts": [
    {
      "artist": "Air",
      "name": "Ticket Header",
      "venue": "Day Air Ballpark",
      "city": "Dayton",
      "country": "United States Of America",
      "country_code": "US",
      "date": "2024-12-28",
      "time": "20:00:00",
      "url": "",
      "source": "Ticketmaster",
      "id": "Za5ju3rKuqZBJgjq5pOaFFFEqPvUlxQno"
    },
    {
      "artist": "Air",
      "name": "2025 ACC Men's Basketball - SEMIFINALS",
      "venue": "Spectrum Center",
      "city": "Charlotte",
      "country": "United States Of America",
      "country_code": "US",
      "date": "2024-12-29",
      "time": "14:00:00",
      "url": "",
      "source": "Ticketmaster",
      "id": "Za5ju3rKuqZB906bmeRyuilTO9VQsh_KC"
    },
    {
      "artist": "Air",
      "name": "2025 ACC Men's Basketball - CHAMPIONSHIP",
      "venue": "Spectrum Center",
      "city": "Charlotte",
      "country": "United States Of America",
      "country_code": "US",
      "date": "2024-12-30",
      "time": "14:00:00",
      "url": "",
      "source": "Ticketmaster",
      "id": "Za5ju3rKuqZDe0WHQolYWevznTl7Jjpmzn"
    },
    {
      "artist": "Air",
      "name": "2024 Group Deposit",
      "venue": "Day Air Ballpark",
      "city": "Dayton",
      "country": "United States Of America",
      "country_code": "US",
      "date": "2024-12-30",
      "time": "20:00:00",
      "url": "",
      "source": "Ticketmaster",
      "id": "Za5ju3rKuqZBV3j89ef_6KDdoTPSVnGyd"
    },
    {
      "artist": "Air",
      "name": "Aerosmith - Club Signature Air Canada",
      "venue": "Bell Centre",
      "city": "Montréal",
      "country": "Can",
      "country_code": "CAN",
      "date": "2024-12-31",
      "time": "19:00:00",
      "url": "",
      "source": "Ticketmaster",
      "id": "Za5ju3rKuqZDeykL_fV2t2EQuvl_nqW8Rd"
    },
    {
      "artist": "Air",
      "name": "İlkay Akkaya",
      "venue": "Bursa Kültür Park Open Air Theatre",
      "city": "Bursa",
      "country": "Turkey",
      "country_code": "TR",
      "date": "2025-10-23",
      "time": "20:30:00",
      "url": "https://www.biletix.com/performance/4MOV7/001/TURKIYE/tr",
      "source": "Ticketmaster",
      "id": "Z2HyzZyMZA9_OFvve"
    },
    {
      "artist": "Air",
      "name": "Melek Mosso",
      "venue": "İzmir Kültürpark Open Air Theatre",
      "city": "İzmir",
      "country": "Turkey",
      "country_code": "TR",
      "date": "2025-10-23",
      "time": "21:00:00",
      "url": "https://www.biletix.com/performance/4JBDV/001/TURKIYE/tr",
      "source": "Ticketmaster",
      "id": "Z2HyzZyMZAfGCOvve"
    },
    {
      "artist": "Air",
      "name": "Jean-Paul Rouve – L’air de rien",
      "venue": "Cirque Royal - Koninklijk Circus",
      "city": "Brussels",
      "country": "Belgium",
      "country_code": "BE",
      "date": "2025-10-23",
      "time": "20:00:00",
      "url": "https://www.ticketmaster.be/event/jean-paul-rouve--lair-de-rien-tickets/64815",
      "source": "Ticketmaster",
      "id": "Z698xZG2Za2VR"
    },
    {
      "artist": "Air",
      "name": "Fatma Turgut",
      "venue": "Antalya Open Air",
      "city": "Antalya",
      "country": "Turkey",
      "country_code": "TR",
      "date": "2025-10-23",
      "time": "21:00:00",
      "url": "https://www.biletix.com/performance/4JBE3/001/TURKIYE/tr",
      "source": "Ticketmaster",
      "id": "ZaHyzZyMZAfG7RNZv"
    },
    {
      "artist": "Air",
      "name": "Ariane Moffatt - Airs de jeux",
      "venue": "MTELUS",
      "city": "Montreal",
      "country": "Canada",
      "country_code": "CA",
      "date": "2025-10-23",
      "time": "20:00:00",
      "url": "https://www.ticketmaster.ca/ariane-moffatt-airs-de-jeux-montreal-quebec-10-23-2025/event/3100626EE43050CA",
      "source": "Ticketmaster",
      "id": "1Ad7ZbJGkD0GAd1"
    },
    {
      "artist": "Air",
      "name": "Phil Wickham - Air1 Worship Now Tour",
      "venue": "Golden 1 Center",
      "city": "Sacramento",
      "country": "United States Of America",
      "country_code": "US",
      "date": "2025-10-23",
      "time": "19:00:00",
      "url": "https://www.ticketmaster.com/phil-wickham-air1-worship-now-tour-sacramento-california-10-23-2025/event/1C006273E03F3F6B",
      "source": "Ticketmaster",
      "id": "G5vYZbE2O2SWl"
    },
    {
      "artist": "Air",
      "name": "Air1 Worship Now Tour",
      "venue": "Golden 1 Center",
      "city": "Sacramento",
      "country": "United States Of America",
      "country_code": "US",
      "date": "2025-10-23",
      "time": "19:00:00",
      "url": "",
      "source": "Ticketmaster",
      "id": "Za5ju3rKuqZDdsL9G1vLsChbpOO2XFv3Gn"
    },
    {
      "artist": "Air",
      "name": "Melike Şahin",
      "venue": "Bursa Kültür Park Open Air Theatre",
      "city": "Bursa",
      "country": "Turkey",
      "country_code": "TR",
      "date": "2025-10-24",
      "time": "21:00:00",
      "url": "https://www.biletix.com/performance/45AY5/001/TURKIYE/tr",
      "source": "Ticketmaster",
      "id": "Z2HyzZyMZAk5Nkvve"
    },
    {
      "artist": "Air",
      "name": "Sıla",
      "venue": "Antalya Open Air",
      "city": "Antalya",
      "country": "Turkey",
      "country_code": "TR",
      "date": "2025-10-24",
      "time": "21:00:00",
      "url": "https://www.biletix.com/performance/41946/001/TURKIYE/tr",
      "source": "Ticketmaster",
      "id": "Z6HyzZyMZ1kvvPkZv"
    },
    {
      "artist": "Air",
      "name": "Teoman",
      "venue": "İzmir Kültürpark Open Air Theatre",
      "city": "İzmir",
      "country": "Turkey",
      "country_code": "TR",
      "date": "2025-10-24",
      "time": "21:00:00",
      "url": "https://www.biletix.com/performance/4JB71/001/TURKIYE/tr",
      "source": "Ticketmaster",
      "id": "ZaHyzZyMZAfG7csZv"
    },
    {
      "artist": "Air",
      "name": "RIT Tigers Men's Hockey vs. Air Force Academy Falcons Hockey",
      "venue": "Gene Polisseni Center",
      "city": "Rochester",
      "country": "United States Of America",
      "country_code": "US",
      "date": "2025-10-24",
      "time": "19:05:00",
      "url": "https://www.ticketmaster.com/event/Z7r9jZ1A7_t4f",
      "source": "Ticketmaster",
      "id": "Z7r9jZ1A7_t4f"
    },
    {
      "artist": "Air",
      "name": "Halloween Spooktacular Hot Air Balloon Festival",
      "venue": "Salt River Fields at Talking Stick",
      "city": "Scottsdale",
      "country": "United States Of America",
      "country_code": "US",
      "date": "2025-10-24",
      "time": "17:00:00",
      "url": "https://www.ticketweb.com/event/halloween-spooktacular-hot-air-balloon-salt-river-fields-at-talking-tickets/14440593",
      "source": "Ticketmaster",
      "id": "rZ7HnEZ1AfoZpK"
    },
    {
      "artist": "Air",
      "name": "Phil Wickham - Air1 Worship Now Tour",
      "venue": "Reno Events Center",
      "city": "Reno",
      "country": "United States Of America",
      "country_code": "US",
      "date": "2025-10-24",
      "time": "19:00:00",
      "url": "https://www.ticketmaster.com/phil-wickham-air1-worship-now-tour-reno-nevada-10-24-2025/event/17006278C2BC3305",
      "source": "Ticketmaster",
      "id": "1A9ZkazGkdeRdGA"
    },
    {
      "artist": "Air",
      "name": "The Witcher in Concert",
      "venue": "Cal Coast Credit Union Open Air Theatre at SDSU",
      "city": "San Diego",
      "country": "United States Of America",
      "country_code": "US",
      "date": "2025-10-24",
      "time": "20:00:00",
      "url": "https://www.ticketmaster.com/the-witcher-in-concert-san-diego-california-10-24-2025/event/0A0062B5960A3458",
      "source": "Ticketmaster",
      "id": "vvG1IZblppeNob"
    },
    {
      "artist": "Air",
      "name": "DUMAN",
      "venue": "Antalya Open Air",
      "city": "Antalya",
      "country": "Turkey",
      "country_code": "TR",
      "date": "2025-10-25",
      "time": "21:00:00",
      "url": "https://www.biletix.com/performance/4PMY1/001/TURKIYE/tr",
      "source": "Ticketmaster",
      "id": "Z2HyzZyMZAQ9Nevve"
    },
    {
      "artist": "Air",
      "name": "Ajda Pekkan",
      "venue": "Bursa Kültür Park Open Air Theatre",
      "city": "Bursa",
      "country": "Turkey",
      "country_code": "TR",
      "date": "2025-10-25",
      "time": "21:00:00",
      "url": "https://www.biletix.com/performance/4LWE8/001/TURKIYE/tr",
      "source": "Ticketmaster",
      "id": "Z2HyzZyMZAp-2avve"
    },
    {
      "artist": "Air",
      "name": "Sagopa Kajmer",
      "venue": "İzmir Kültürpark Open Air Theatre",
      "city": "İzmir",
      "country": "Turkey",
      "country_code": "TR",
      "date": "2025-10-25",
      "time": "21:00:00",
      "url": "https://www.biletix.com/performance/4SKRF/001/TURKIYE/tr",
      "source": "Ticketmaster",
      "id": "Z2HyzZyMZAq4j8vve"
    },
    {
      "artist": "Air",
      "name": "RIT Tigers Men's Hockey vs. Air Force Academy Falcons Hockey",
      "venue": "Gene Polisseni Center",
      "city": "Rochester",
      "country": "United States Of America",
      "country_code": "US",
      "date": "2025-10-25",
      "time": "17:05:00",
      "url": "https://www.ticketmaster.com/event/Z7r9jZ1A7_t44",
      "source": "Ticketmaster",
      "id": "Z7r9jZ1A7_t44"
    },
    {
      "artist": "Air",
      "name": "Halloween Spooktacular Hot Air Balloon Festival",
      "venue": "Salt River Fields at Talking Stick",
      "city": "Scottsdale",
      "country": "United States Of America",
      "country_code": "US",
      "date": "2025-10-25",
      "time": "17:00:00",
      "url": "https://www.ticketweb.com/event/halloween-spooktacular-hot-air-balloon-salt-river-fields-at-talking-tickets/14440673",
      "source": "Ticketmaster",
      "id": "rZ7HnEZ1AfoZ_S"
    },
    {
      "artist": "Air",
      "name": "Air Supply: 50th Anniversary Celebration",
      "venue": "Hard Rock Live at Etess Arena",
      "city": "Atlantic City",
      "country": "United States Of America",
      "country_code": "US",
      "date": "2025-10-25",
      "time": "20:00:00",
      "url": "https://www.ticketmaster.com/air-supply-50th-anniversary-celebration-atlantic-city-new-jersey-10-25-2025/event/020062A7B28E46C2",
      "source": "Ticketmaster",
      "id": "vvG1FZbnrwN0he"
    },
    {
      "artist": "Air",
      "name": "Back In Town Festival",
      "venue": "Maximum Uniq Open Air",
      "city": "İstanbul",
      "country": "Turkey",
      "country_code": "TR",
      "date": "2025-10-26",
      "time": "21:00:00",
      "url": "https://www.biletix.com/performance/4DTB9/001/TURKIYE/tr",
      "source": "Ticketmaster",
      "id": "Z2HyzZyMZACrG1vve"
    },
    {
      "artist": "Air",
      "name": "Air Supply - 50th Anniversary Celebration",
      "venue": "New Jersey Performing Arts Center",
      "city": "Newark",
      "country": "United States Of America",
      "country_code": "US",
      "date": "2025-10-26",
      "time": "19:00:00",
      "url": "https://www.ticketmaster.com/air-supply-50th-anniversary-celebration-newark-new-jersey-10-26-2025/event/000062BEA1CE1953",
      "source": "Ticketmaster",
      "id": "k7vGFblB-S-PK"
    },
    {
      "artist": "Air",
      "name": "Halloween Spooktacular Hot Air Balloon Festival",
      "venue": "Salt River Fields at Talking Stick",
      "city": "Scottsdale",
      "country": "United States Of America",
      "country_code": "US",
      "date": "2025-10-26",
      "time": "17:00:00",
      "url": "https://www.ticketweb.com/event/halloween-spooktacular-hot-air-balloon-salt-river-fields-at-talking-tickets/14440713",
      "source": "Ticketmaster",
      "id": "rZ7HnEZ1AfoZjK"
    },
    {
      "artist": "Air",
      "name": "Phil Wickham - Air1 Worship Now Tour",
      "venue": "Angel Of The Winds Arena",
      "city": "Everett",
      "country": "United States Of America",
      "country_code": "US",
      "date": "2025-10-26",
      "time": "19:00:00",
      "url": "https://www.ticketmaster.com/phil-wickham-air1-worship-now-tour-everett-washington-10-26-2025/event/0F006278D58F2EC2",
      "source": "Ticketmaster",
      "id": "vvG1HZbEN4NwDe"
    },
    {
      "artist": "Air",
      "name": "Gökhan Çınar - Katarsis - Gel Yeniden Başlayalım",
      "venue": "Antalya Open Air",
      "city": "Antalya",
      "country": "Turkey",
      "country_code": "TR",
      "date": "2025-10-27",
      "time": "20:00:00",
      "url": "https://www.biletix.com/performance/4YS21/001/TURKIYE/tr",
      "source": "Ticketmaster",
      "id": "Z1HyzZyMZANqaAFa"
    },
    {
      "artist": "Air",
      "name": "Air Force Academy Falcons Hockey vs. Brown University Bears Hockey",
      "venue": "Cadet Ice Arena",
      "city": "USAF Academy",
      "country": "United States Of America",
      "country_code": "US",
      "date": "2025-10-31",
      "time": "",
      "url": "https://www.ticketmaster.com/event/Z7r9jZ1A7_IFU",
      "source": "Ticketmaster",
      "id": "Z7r9jZ1A7_IFU"
    },
    {
      "artist": "Air",
      "name": "Ati242",
      "venue": "Bursa Kültür Park Open Air Theatre",
      "city": "Bursa",
      "country": "Turkey",
      "country_code": "TR",
      "date": "2025-10-31",
      "time": "21:00:00",
      "url": "https://www.biletix.com/performance/4AP62/001/TURKIYE/tr",
      "source": "Ticketmaster",
      "id": "Z1HyzZyMZA5Qa2Fs"
    },
    {
      "artist": "Air",
      "name": "Koray Avcı",
      "venue": "Antalya Open Air",
      "city": "Antalya",
      "country": "Turkey",
      "country_code": "TR",
      "date": "2025-10-31",
      "time": "21:00:00",
      "url": "https://www.biletix.com/performance/4JBEN/001/TURKIYE/tr",
      "source": "Ticketmaster",
      "id": "Z2HyzZyMZAfG2bvve"
    },
    {
      "artist": "Air",
      "name": "Ajda Pekkan",
      "venue": "İzmir Kültürpark Open Air Theatre",
      "city": "İzmir",
      "country": "Turkey",
      "country_code": "TR",
      "date": "2025-10-31",
      "time": "21:00:00",
      "url": "https://www.biletix.com/performance/4LWE9/001/TURKIYE/tr",
      "source": "Ticketmaster",
      "id": "Z2HyzZyMZAp-21vve"
    },
    {
      "artist": "Air",
      "name": "Air Force Academy Falcons Hockey vs. Brown University Bears Hockey",
      "venue": "Cadet Ice Arena",
      "city": "USAF Academy",
      "country": "United States Of America",
      "country_code": "US",
      "date": "2025-11-01",
      "time": "",
      "url": "https://www.ticketmaster.com/event/Z7r9jZ1A7_IFM",
      "source": "Ticketmaster",
      "id": "Z7r9jZ1A7_IFM"
    },
    {
      "artist": "Air",
      "name": "Bone Thugs N Harmony w/ B.Well",
      "venue": "Val Air Ballroom",
      "city": "West Des Moines",
      "country": "United States Of America",
      "country_code": "US",
      "date": "2025-10-31",
      "time": "19:00:00",
      "url": "https://www.ticketmaster.com/event/Z7r9jZ1A7jJGb",
      "source": "Ticketmaster",
      "id": "Z7r9jZ1A7jJGb"
    },
    {
      "artist": "Air",
      "name": "Air Force Academy Falcons Football vs. Army Black Knights Football",
      "venue": "Falcon Stadium",
      "city": "Colorado Springs",
      "country": "United States Of America",
      "country_code": "US",
      "date": "2025-11-01",
      "time": "",
      "url": "https://www.ticketmaster.com/event/Z7r9jZ1A7pv7A",
      "source": "Ticketmaster",
      "id": "Z7r9jZ1A7pv7A"
    },
    {
      "artist": "Air",
      "name": "2025 Fun Zone",
      "venue": "Day Air Ballpark",
      "city": "Dayton",
      "country": "United States Of America",
      "country_code": "US",
      "date": "2025-10-31",
      "time": "20:00:00",
      "url": "",
      "source": "Ticketmaster",
      "id": "Za5ju3rKuqZDekS6hSJ9WuVDzSZSKrZ2lS"
    },
    {
      "artist": "Air",
      "name": "VIP Anjunadeep Open Air Mexico City",
      "venue": "Velodromo",
      "city": "Ciudad de México",
      "country": "Mexico",
      "country_code": "MX",
      "date": "2025-10-31",
      "time": "20:00:00",
      "url": "https://www.ticketmaster.com.mx/vip-anjunadeep-open-air-mexico-city-ciudad-de-mexico-31-10-2025/event/3D0062A915344958",
      "source": "Ticketmaster",
      "id": "G5dVZbn04u7Pb"
    },
    {
      "artist": "Air",
      "name": "General Anjunadeep Open Air Mexico City",
      "venue": "Velodromo",
      "city": "Ciudad de México",
      "country": "Mexico",
      "country_code": "MX",
      "date": "2025-10-31",
      "time": "20:00:00",
      "url": "https://www.ticketmaster.com.mx/general-anjunadeep-open-air-mexico-city-ciudad-de-mexico-31-10-2025/event/3D0062AD87560A53",
      "source": "Ticketmaster",
      "id": "G5dVZbnU64OtK"
    },
    {
      "artist": "Air",
      "name": "Air Supply 50th Anniversary Celebration",
      "venue": "Music Hall Center",
      "city": "Detroit",
      "country": "United States Of America",
      "country_code": "US",
      "date": "2025-11-01",
      "time": "20:00:00",
      "url": "https://www.ticketmaster.com/air-supply-50th-anniversary-celebration-detroit-michigan-11-01-2025/event/08006184EE8F553E",
      "source": "Ticketmaster",
      "id": "vv1AFZkk7GkdmNgfX"
    },
    {
      "artist": "Air",
      "name": "Prof w/ Snotty Nose Rez Kids",
      "venue": "Val Air Ballroom",
      "city": "West Des Moines",
      "country": "United States Of America",
      "country_code": "US",
      "date": "2025-11-01",
      "time": "20:00:00",
      "url": "https://www.ticketmaster.com/event/Z7r9jZ1A7QoGV",
      "source": "Ticketmaster",
      "id": "Z7r9jZ1A7QoGV"
    },
    {
      "artist": "Air",
      "name": "Air Supply - 50th Anniversary Celebration",
      "venue": "The Pantheon at Caesars Virginia",
      "city": "Danville",
      "country": "United States Of America",
      "country_code": "US",
      "date": "2025-11-02",
      "time": "19:00:00",
      "url": "https://www.ticketmaster.com/air-supply-50th-anniversary-celebration-danville-virginia-11-02-2025/event/010062CAC90A4BBE",
      "source": "Ticketmaster",
      "id": "vvG17Zbilae0mX"
    },
    {
      "artist": "Air",
      "name": "Mora: Lo Mismo de la Otra Vez Tour 2025",
      "venue": "Cal Coast Credit Union Open Air Theatre at SDSU",
      "city": "San Diego",
      "country": "United States Of America",
      "country_code": "US",
      "date": "2025-11-02",
      "time": "20:00:00",
      "url": "https://www.ticketmaster.com/mora-lo-mismo-de-la-otra-san-diego-california-11-02-2025/event/0A0062B6997431D5",
      "source": "Ticketmaster",
      "id": "vvG1IZblQ_qd64"
    },
    {
      "artist": "Air",
      "name": "FEVO Payments",
      "venue": "Day Air Ballpark",
      "city": "Dayton",
      "country": "United States Of America",
      "country_code": "US",
      "date": "2025-11-04",
      "time": "20:00:00",
      "url": "",
      "source": "Ticketmaster",
      "id": "Za5ju3rKuqZDvNRkR34Vo2jn4DSZkn0tIS"
    },
    {
      "artist": "Air",
      "name": "Kenan Doğulu",
      "venue": "İzmir Kültürpark Open Air Theatre",
      "city": "İzmir",
      "country": "Turkey",
      "country_code": "TR",
      "date": "2025-11-05",
      "time": "21:00:00",
      "url": "https://www.biletix.com/performance/4DTNR/001/TURKIYE/tr",
      "source": "Ticketmaster",
      "id": "Z2HyzZyMZACrbjvve"
    },
    {
      "artist": "Air",
      "name": "Karsu",
      "venue": "İzmir Kültürpark Open Air Theatre",
      "city": "İzmir",
      "country": "Turkey",
      "country_code": "TR",
      "date": "2025-11-06",
      "time": "21:00:00",
      "url": "https://www.biletix.com/performance/4MAYG/001/TURKIYE/tr",
      "source": "Ticketmaster",
      "id": "Z2HyzZyMZA95Novve"
    },
    {
      "artist": "Air",
      "name": "Ally ACC Women's Soccer Semi-Finals",
      "venue": "WakeMed Soccer Park",
      "city": "Cary",
      "country": "United States Of America",
      "country_code": "US",
      "date": "2025-11-06",
      "time": "17:30:00",
      "url": "",
      "source": "Ticketmaster",
      "id": "Za5ju3rKuqZDdCljECoIadHyEuQ21PuHt9"
    },
    {
      "artist": "Air",
      "name": "Hippie Sabotage",
      "venue": "Val Air Ballroom",
      "city": "West Des Moines",
      "country": "United States Of America",
      "country_code": "US",
      "date": "2025-11-06",
      "time": "20:00:00",
      "url": "https://www.ticketmaster.com/event/Z7r9jZ1A7Qoup",
      "source": "Ticketmaster",
      "id": "Z7r9jZ1A7Qoup"
    },
    {
      "artist": "Air",
      "name": "Private Hire Igloos with thanks to Air Canada",
      "venue": "Battersea Power Station",
      "city": "London",
      "country": "Great Britain",
      "country_code": "GB",
      "date": "2025-11-07",
      "time": "10:00:00",
      "url": "https://www.universe.com/events/private-hire-igloos-with-thanks-to-air-canada-tickets-V8T3ZB?ref=ticketmaster",
      "source": "Ticketmaster",
      "id": "LvZ18QauHDVGycYZvL5hA"
    },
    {
      "artist": "Air",
      "name": "Private Hire Igloos with thanks to Air Canada",
      "venue": "Battersea Power Station",
      "city": "London",
      "country": "Great Britain",
      "country_code": "GB",
      "date": "2025-11-07",
      "time": "11:00:00",
      "url": "https://www.universe.com/events/private-hire-igloos-with-thanks-to-air-canada-tickets-V8T3ZB?ref=ticketmaster",
      "source": "Ticketmaster",
      "id": "LvZ18QauHDVGycYZvL5hk"
    },
    {
      "artist": "Air",
      "name": "Private Hire Igloos with thanks to Air Canada",
      "venue": "Battersea Power Station",
      "city": "London",
      "country": "Great Britain",
      "country_code": "GB",
      "date": "2025-11-07",
      "time": "12:00:00",
      "url": "https://www.universe.com/events/private-hire-igloos-with-thanks-to-air-canada-tickets-V8T3ZB?ref=ticketmaster",
      "source": "Ticketmaster",
      "id": "LvZ18QauHDVGycYZvL5h6"
    },
    {
      "artist": "Air",
      "name": "Private Hire Igloos with thanks to Air Canada",
      "venue": "Battersea Power Station",
      "city": "London",
      "country": "Great Britain",
      "country_code": "GB",
      "date": "2025-11-07",
      "time": "13:00:00",
      "url": "https://www.universe.com/events/private-hire-igloos-with-thanks-to-air-canada-tickets-V8T3ZB?ref=ticketmaster",
      "source": "Ticketmaster",
      "id": "LvZ18QauHDVGycYZvL5hF"
    },
    {
      "artist": "Air",
      "name": "Private Hire Igloos with thanks to Air Canada",
      "venue": "Battersea Power Station",
      "city": "London",
      "country": "Great Britain",
      "country_code": "GB",
      "date": "2025-11-07",
      "time": "14:00:00",
      "url": "https://www.universe.com/events/private-hire-igloos-with-thanks-to-air-canada-tickets-V8T3ZB?ref=ticketmaster",
      "source": "Ticketmaster",
      "id": "LvZ18QauHDVGycYZvL5ha"
    },
    {
      "artist": "Air",
      "name": "Private Hire Igloos with thanks to Air Canada",
      "venue": "Battersea Power Station",
      "city": "London",
      "country": "Great Britain",
      "country_code": "GB",
      "date": "2025-11-07",
      "time": "15:00:00",
      "url": "https://www.universe.com/events/private-hire-igloos-with-thanks-to-air-canada-tickets-V8T3ZB?ref=ticketmaster",
      "source": "Ticketmaster",
      "id": "LvZ18QauHDVGycYZvL5h1"
    },
    {
      "artist": "Air",
      "name": "Private Hire Igloos with thanks to Air Canada",
      "venue": "Battersea Power Station",
      "city": "London",
      "country": "Great Britain",
      "country_code": "GB",
      "date": "2025-11-07",
      "time": "16:00:00",
      "url": "https://www.universe.com/events/private-hire-igloos-with-thanks-to-air-canada-tickets-V8T3ZB?ref=ticketmaster",
      "source": "Ticketmaster",
      "id": "LvZ18QauHDVGycYZvL5h5"
    },
    {
      "artist": "Air",
      "name": "Private Hire Igloos with thanks to Air Canada",
      "venue": "Battersea Power Station",
      "city": "London",
      "country": "Great Britain",
      "country_code": "GB",
      "date": "2025-11-07",
      "time": "17:00:00",
      "url": "https://www.universe.com/events/private-hire-igloos-with-thanks-to-air-canada-tickets-V8T3ZB?ref=ticketmaster",
      "source": "Ticketmaster",
      "id": "LvZ18QauHDVGycYZvL5hG"
    },
    {
      "artist": "Air",
      "name": "Private Hire Igloos with thanks to Air Canada",
      "venue": "Battersea Power Station",
      "city": "London",
      "country": "Great Britain",
      "country_code": "GB",
      "date": "2025-11-07",
      "time": "18:00:00",
      "url": "https://www.universe.com/events/private-hire-igloos-with-thanks-to-air-canada-tickets-V8T3ZB?ref=ticketmaster",
      "source": "Ticketmaster",
      "id": "LvZ18QauHDVGycYZvL5hu"
    },
    {
      "artist": "Air",
      "name": "Özcan Deniz",
      "venue": "Antalya Open Air",
      "city": "Antalya",
      "country": "Turkey",
      "country_code": "TR",
      "date": "2025-11-07",
      "time": "21:00:00",
      "url": "https://www.biletix.com/performance/4ONX8/001/TURKIYE/tr",
      "source": "Ticketmaster",
      "id": "Z2HyzZyMZA_bxavve"
    },
    {
      "artist": "Air",
      "name": "Private Hire Igloos with thanks to Air Canada",
      "venue": "Battersea Power Station",
      "city": "London",
      "country": "Great Britain",
      "country_code": "GB",
      "date": "2025-11-07",
      "time": "19:00:00",
      "url": "https://www.universe.com/events/private-hire-igloos-with-thanks-to-air-canada-tickets-V8T3ZB?ref=ticketmaster",
      "source": "Ticketmaster",
      "id": "LvZ18QauHDVGycYZvL5hC"
    },
    {
      "artist": "Air",
      "name": "Private Hire Igloos with thanks to Air Canada",
      "venue": "Battersea Power Station",
      "city": "London",
      "country": "Great Britain",
      "country_code": "GB",
      "date": "2025-11-07",
      "time": "20:00:00",
      "url": "https://www.universe.com/events/private-hire-igloos-with-thanks-to-air-canada-tickets-V8T3ZB?ref=ticketmaster",
      "source": "Ticketmaster",
      "id": "LvZ18QauHDVGycYZvL5h2"
    },
    {
      "artist": "Air",
      "name": "Private Hire Igloos with thanks to Air Canada",
      "venue": "Battersea Power Station",
      "city": "London",
      "country": "Great Britain",
      "country_code": "GB",
      "date": "2025-11-07",
      "time": "21:00:00",
      "url": "https://www.universe.com/events/private-hire-igloos-with-thanks-to-air-canada-tickets-V8T3ZB?ref=ticketmaster",
      "source": "Ticketmaster",
      "id": "LvZ18QauHDVGycYZvL5h8"
    },
    {
      "artist": "Air",
      "name": "Sacred Heart Pioneers Men's Ice Hockey vs. Air Force Falcons Mens Hockey",
      "venue": "Martire Family Arena ",
      "city": "Fairfield",
      "country": "United States Of America",
      "country_code": "US",
      "date": "2025-11-07",
      "time": "19:00:00",
      "url": "https://www.ticketmaster.com/sacred-heart-pioneers-mens-ice-hockey-fairfield-connecticut-11-07-2025/event/1D0062FFC3D239F0",
      "source": "Ticketmaster",
      "id": "G5vVZbRTdVNEY"
    },
    {
      "artist": "Air",
      "name": "San Jose State Spartans Football vs. Air Force Academy Falcons Football",
      "venue": "CEFCU Stadium",
      "city": "San Jose",
      "country": "United States Of America",
      "country_code": "US",
      "date": "2025-11-08",
      "time": "",
      "url": "https://www.ticketmaster.com/event/Z7r9jZ1A7pvZp",
      "source": "Ticketmaster",
      "id": "Z7r9jZ1A7pvZp"
    },
    {
      "artist": "Air",
      "name": "Air Supply 50th Anniversary Celebration",
      "venue": "Talking Stick Resort",
      "city": "Scottsdale",
      "country": "United States Of America",
      "country_code": "US",
      "date": "2025-11-07",
      "time": "20:00:00",
      "url": "https://www.ticketmaster.com/air-supply-50th-anniversary-celebration-scottsdale-arizona-11-07-2025/event/19006284B9FA3C83",
      "source": "Ticketmaster",
      "id": "1A_Zk17GkeyXNwd"
    },
    {
      "artist": "Air",
      "name": "Miguel Bosé: Importante Tour 2025-2026",
      "venue": "Cal Coast Credit Union Open Air Theatre at SDSU",
      "city": "San Diego",
      "country": "United States Of America",
      "country_code": "US",
      "date": "2025-11-07",
      "time": "19:00:00",
      "url": "https://www.ticketmaster.com/miguel-bose-importante-tour-20252026-san-diego-california-11-07-2025/event/0A00616FC2CE4683",
      "source": "Ticketmaster",
      "id": "vvG1IZbpTeS0Qd"
    },
    {
      "artist": "Air",
      "name": "Private Hire Igloos with thanks to Air Canada",
      "venue": "Battersea Power Station",
      "city": "London",
      "country": "Great Britain",
      "country_code": "GB",
      "date": "2025-11-08",
      "time": "10:00:00",
      "url": "https://www.universe.com/events/private-hire-igloos-with-thanks-to-air-canada-tickets-V8T3ZB?ref=ticketmaster",
      "source": "Ticketmaster",
      "id": "LvZ18QauHDVGycYZvL5ho"
    },
    {
      "artist": "Air",
      "name": "Private Hire Igloos with thanks to Air Canada",
      "venue": "Battersea Power Station",
      "city": "London",
      "country": "Great Britain",
      "country_code": "GB",
      "date": "2025-11-08",
      "time": "11:00:00",
      "url": "https://www.universe.com/events/private-hire-igloos-with-thanks-to-air-canada-tickets-V8T3ZB?ref=ticketmaster",
      "source": "Ticketmaster",
      "id": "LvZ18QauHDVGycYZvL5h3"
    },
    {
      "artist": "Air",
      "name": "Private Hire Igloos with thanks to Air Canada",
      "venue": "Battersea Power Station",
      "city": "London",
      "country": "Great Britain",
      "country_code": "GB",
      "date": "2025-11-08",
      "time": "12:00:00",
      "url": "https://www.universe.com/events/private-hire-igloos-with-thanks-to-air-canada-tickets-V8T3ZB?ref=ticketmaster",
      "source": "Ticketmaster",
      "id": "LvZ18QauHDVGycYZvL5hK"
    },
    {
      "artist": "Air",
      "name": "Private Hire Igloos with thanks to Air Canada",
      "venue": "Battersea Power Station",
      "city": "London",
      "country": "Great Britain",
      "country_code": "GB",
      "date": "2025-11-08",
      "time": "13:00:00",
      "url": "https://www.universe.com/events/private-hire-igloos-with-thanks-to-air-canada-tickets-V8T3ZB?ref=ticketmaster",
      "source": "Ticketmaster",
      "id": "LvZ18QauHDVGycYZvL5hf"
    },
    {
      "artist": "Air",
      "name": "Private Hire Igloos with thanks to Air Canada",
      "venue": "Battersea Power Station",
      "city": "London",
      "country": "Great Britain",
      "country_code": "GB",
      "date": "2025-11-08",
      "time": "14:00:00",
      "url": "https://www.universe.com/events/private-hire-igloos-with-thanks-to-air-canada-tickets-V8T3ZB?ref=ticketmaster",
      "source": "Ticketmaster",
      "id": "LvZ18QauHDVGycYZvL5h4"
    },
    {
      "artist": "Air",
      "name": "Private Hire Igloos with thanks to Air Canada",
      "venue": "Battersea Power Station",
      "city": "London",
      "country": "Great Britain",
      "country_code": "GB",
      "date": "2025-11-08",
      "time": "15:00:00",
      "url": "https://www.universe.com/events/private-hire-igloos-with-thanks-to-air-canada-tickets-V8T3ZB?ref=ticketmaster",
      "source": "Ticketmaster",
      "id": "LvZ18QauHDVGycYZvL5hp"
    },
    {
      "artist": "Air",
      "name": "Private Hire Igloos with thanks to Air Canada",
      "venue": "Battersea Power Station",
      "city": "London",
      "country": "Great Britain",
      "country_code": "GB",
      "date": "2025-11-08",
      "time": "16:00:00",
      "url": "https://www.universe.com/events/private-hire-igloos-with-thanks-to-air-canada-tickets-V8T3ZB?ref=ticketmaster",
      "source": "Ticketmaster",
      "id": "LvZ18QauHDVGycYZvL5h9"
    },
    {
      "artist": "Air",
      "name": "Private Hire Igloos with thanks to Air Canada",
      "venue": "Battersea Power Station",
      "city": "London",
      "country": "Great Britain",
      "country_code": "GB",
      "date": "2025-11-08",
      "time": "17:00:00",
      "url": "https://www.universe.com/events/private-hire-igloos-with-thanks-to-air-canada-tickets-V8T3ZB?ref=ticketmaster",
      "source": "Ticketmaster",
      "id": "LvZ18QauHDVGycYZvL5hb"
    },
    {
      "artist": "Air",
      "name": "mor ve ötesi",
      "venue": "Antalya Open Air",
      "city": "Antalya",
      "country": "Turkey",
      "country_code": "TR",
      "date": "2025-11-08",
      "time": "20:00:00",
      "url": "https://www.biletix.com/performance/41959/001/TURKIYE/tr",
      "source": "Ticketmaster",
      "id": "Z6HyzZyMZ1kvvP_Zv"
    },
    {
      "artist": "Air",
      "name": "Private Hire Igloos with thanks to Air Canada",
      "venue": "Battersea Power Station",
      "city": "London",
      "country": "Great Britain",
      "country_code": "GB",
      "date": "2025-11-08",
      "time": "18:00:00",
      "url": "https://www.universe.com/events/private-hire-igloos-with-thanks-to-air-canada-tickets-V8T3ZB?ref=ticketmaster",
      "source": "Ticketmaster",
      "id": "LvZ18QauHDVGycYZvL5h_"
    },
    {
      "artist": "Air",
      "name": "An Epic Symphony & maNga",
      "venue": "İzmir Kültürpark Open Air Theatre",
      "city": "İzmir",
      "country": "Turkey",
      "country_code": "TR",
      "date": "2025-11-08",
      "time": "21:00:00",
      "url": "https://www.biletix.com/performance/4EABC/001/TURKIYE/tr",
      "source": "Ticketmaster",
      "id": "Z6HyzZyMZGkvCnHZv"
    },
    {
      "artist": "Air",
      "name": "Private Hire Igloos with thanks to Air Canada",
      "venue": "Battersea Power Station",
      "city": "London",
      "country": "Great Britain",
      "country_code": "GB",
      "date": "2025-11-08",
      "time": "19:00:00",
      "url": "https://www.universe.com/events/private-hire-igloos-with-thanks-to-air-canada-tickets-V8T3ZB?ref=ticketmaster",
      "source": "Ticketmaster",
      "id": "LvZ18QauHDVGycYZvL5hQ"
    },
    {
      "artist": "Air",
      "name": "Güneş",
      "venue": "Antalya Open Air",
      "city": "Antalya",
      "country": "Turkey",
      "country_code": "TR",
      "date": "2025-11-08",
      "time": "22:00:00",
      "url": "https://www.biletix.com/performance/41925/001/TURKIYE/tr",
      "source": "Ticketmaster",
      "id": "Z6HyzZyMZ1kvv0PZv"
    },
    {
      "artist": "Air",
      "name": "Private Hire Igloos with thanks to Air Canada",
      "venue": "Battersea Power Station",
      "city": "London",
      "country": "Great Britain",
      "country_code": "GB",
      "date": "2025-11-08",
      "time": "20:00:00",
      "url": "https://www.universe.com/events/private-hire-igloos-with-thanks-to-air-canada-tickets-V8T3ZB?ref=ticketmaster",
      "source": "Ticketmaster",
      "id": "LvZ18QauHDVGycYZvL5hh"
    },
    {
      "artist": "Air",
      "name": "Private Hire Igloos with thanks to Air Canada",
      "venue": "Battersea Power Station",
      "city": "London",
      "country": "Great Britain",
      "country_code": "GB",
      "date": "2025-11-08",
      "time": "21:00:00",
      "url": "https://www.universe.com/events/private-hire-igloos-with-thanks-to-air-canada-tickets-V8T3ZB?ref=ticketmaster",
      "source": "Ticketmaster",
      "id": "LvZ18QauHDVGycYZvL5hj"
    },
    {
      "artist": "Air",
      "name": "Air Force Academy Falcons Mens Basketball vs. Austin Peay Governors Mens Basketball",
      "venue": "Clune Arena",
      "city": "USAF Academy",
      "country": "United States Of America",
      "country_code": "US",
      "date": "2025-11-08",
      "time": "14:00:00",
      "url": "https://www.ticketmaster.com/event/Z7r9jZ1A7j3GU",
      "source": "Ticketmaster",
      "id": "Z7r9jZ1A7j3GU"
    },
    {
      "artist": "Air",
      "name": "Sacred Heart Pioneers Men's Ice Hockey vs. Air Force Falcons Mens Hockey",
      "venue": "Martire Family Arena ",
      "city": "Fairfield",
      "country": "United States Of America",
      "country_code": "US",
      "date": "2025-11-08",
      "time": "17:00:00",
      "url": "https://www.ticketmaster.com/sacred-heart-pioneers-mens-ice-hockey-fairfield-connecticut-11-08-2025/event/1D0062FFC3D439F2",
      "source": "Ticketmaster",
      "id": "G5vVZbRTdgdEw"
    },
    {
      "artist": "Air",
      "name": "Air Force in Concert featuring Hollie Smith",
      "venue": "Michael Fowler Centre",
      "city": "Wellington",
      "country": "New Zealand",
      "country_code": "NZ",
      "date": "2025-11-09",
      "time": "14:30:00",
      "url": "https://www.ticketmaster.co.nz/air-force-in-concert-featuring-hollie-wellington-09-11-2025/event/2400631984620D70",
      "source": "Ticketmaster",
      "id": "1ae8ZbsJ7bOZdCFv"
    },
    {
      "artist": "Air",
      "name": "Bronco",
      "venue": "Cal Coast Credit Union Open Air Theatre at SDSU",
      "city": "San Diego",
      "country": "United States Of America",
      "country_code": "US",
      "date": "2025-11-08",
      "time": "20:00:00",
      "url": "https://www.ticketmaster.com/bronco-san-diego-california-11-08-2025/event/0A006299CD3D5239",
      "source": "Ticketmaster",
      "id": "vvG1IZbtEu24Fy"
    },
    {
      "artist": "Air",
      "name": "Private Hire Igloos with thanks to Air Canada",
      "venue": "Battersea Power Station",
      "city": "London",
      "country": "Great Britain",
      "country_code": "GB",
      "date": "2025-11-09",
      "time": "10:00:00",
      "url": "https://www.universe.com/events/private-hire-igloos-with-thanks-to-air-canada-tickets-V8T3ZB?ref=ticketmaster",
      "source": "Ticketmaster",
      "id": "LvZ18QauHDVGycYZvL5hq"
    },
    {
      "artist": "Air",
      "name": "Private Hire Igloos with thanks to Air Canada",
      "venue": "Battersea Power Station",
      "city": "London",
      "country": "Great Britain",
      "country_code": "GB",
      "date": "2025-11-09",
      "time": "11:00:00",
      "url": "https://www.universe.com/events/private-hire-igloos-with-thanks-to-air-canada-tickets-V8T3ZB?ref=ticketmaster",
      "source": "Ticketmaster",
      "id": "LvZ18QauHDVGycYZvL5hr"
    },
    {
      "artist": "Air",
      "name": "Private Hire Igloos with thanks to Air Canada",
      "venue": "Battersea Power Station",
      "city": "London",
      "country": "Great Britain",
      "country_code": "GB",
      "date": "2025-11-09",
      "time": "12:00:00",
      "url": "https://www.universe.com/events/private-hire-igloos-with-thanks-to-air-canada-tickets-V8T3ZB?ref=ticketmaster",
      "source": "Ticketmaster",
      "id": "LvZ18QauHDVGycYZvL5hL"
    },
    {
      "artist": "Air",
      "name": "Private Hire Igloos with thanks to Air Canada",
      "venue": "Battersea Power Station",
      "city": "London",
      "country": "Great Britain",
      "country_code": "GB",
      "date": "2025-11-09",
      "time": "13:00:00",
      "url": "https://www.universe.com/events/private-hire-igloos-with-thanks-to-air-canada-tickets-V8T3ZB?ref=ticketmaster",
      "source": "Ticketmaster",
      "id": "LvZ18QauHDVGycYZvL5hO"
    },
    {
      "artist": "Air",
      "name": "Private Hire Igloos with thanks to Air Canada",
      "venue": "Battersea Power Station",
      "city": "London",
      "country": "Great Britain",
      "country_code": "GB",
      "date": "2025-11-09",
      "time": "14:00:00",
      "url": "https://www.universe.com/events/private-hire-igloos-with-thanks-to-air-canada-tickets-V8T3ZB?ref=ticketmaster",
      "source": "Ticketmaster",
      "id": "LvZ18QauHDVGycYZvL5h-"
    },
    {
      "artist": "Air",
      "name": "Private Hire Igloos with thanks to Air Canada",
      "venue": "Battersea Power Station",
      "city": "London",
      "country": "Great Britain",
      "country_code": "GB",
      "date": "2025-11-09",
      "time": "15:00:00",
      "url": "https://www.universe.com/events/private-hire-igloos-with-thanks-to-air-canada-tickets-V8T3ZB?ref=ticketmaster",
      "source": "Ticketmaster",
      "id": "LvZ18QauHDVGycYZvL5hx"
    },
    {
      "artist": "Air",
      "name": "Private Hire Igloos with thanks to Air Canada",
      "venue": "Battersea Power Station",
      "city": "London",
      "country": "Great Britain",
      "country_code": "GB",
      "date": "2025-11-09",
      "time": "16:00:00",
      "url": "https://www.universe.com/events/private-hire-igloos-with-thanks-to-air-canada-tickets-V8T3ZB?ref=ticketmaster",
      "source": "Ticketmaster",
      "id": "LvZ18QauHDVGycYZvL5hN"
    },
    {
      "artist": "Air",
      "name": "Private Hire Igloos with thanks to Air Canada",
      "venue": "Battersea Power Station",
      "city": "London",
      "country": "Great Britain",
      "country_code": "GB",
      "date": "2025-11-09",
      "time": "17:00:00",
      "url": "https://www.universe.com/events/private-hire-igloos-with-thanks-to-air-canada-tickets-V8T3ZB?ref=ticketmaster",
      "source": "Ticketmaster",
      "id": "LvZ18QauHDVGycYZvL5h0"
    },
    {
      "artist": "Air",
      "name": "Ally ACC Women's Soccer Finals",
      "venue": "WakeMed Soccer Park",
      "city": "Cary",
      "country": "United States Of America",
      "country_code": "US",
      "date": "2025-11-09",
      "time": "12:00:00",
      "url": "",
      "source": "Ticketmaster",
      "id": "Za5ju3rKuqZB6x6mrs0oulQHkOIUA88Jz"
    },
    {
      "artist": "Air",
      "name": "Private Hire Igloos with thanks to Air Canada",
      "venue": "Battersea Power Station",
      "city": "London",
      "country": "Great Britain",
      "country_code": "GB",
      "date": "2025-11-09",
      "time": "18:00:00",
      "url": "https://www.universe.com/events/private-hire-igloos-with-thanks-to-air-canada-tickets-V8T3ZB?ref=ticketmaster",
      "source": "Ticketmaster",
      "id": "LvZ18QauHDVGycYZvL5hP"
    },
    {
      "artist": "Air",
      "name": "Private Hire Igloos with thanks to Air Canada",
      "venue": "Battersea Power Station",
      "city": "London",
      "country": "Great Britain",
      "country_code": "GB",
      "date": "2025-11-09",
      "time": "19:00:00",
      "url": "https://www.universe.com/events/private-hire-igloos-with-thanks-to-air-canada-tickets-V8T3ZB?ref=ticketmaster",
      "source": "Ticketmaster",
      "id": "LvZ18QauHDVGycYZvL5hJ"
    },
    {
      "artist": "Air",
      "name": "Private Hire Igloos with thanks to Air Canada",
      "venue": "Battersea Power Station",
      "city": "London",
      "country": "Great Britain",
      "country_code": "GB",
      "date": "2025-11-09",
      "time": "20:00:00",
      "url": "https://www.universe.com/events/private-hire-igloos-with-thanks-to-air-canada-tickets-V8T3ZB?ref=ticketmaster",
      "source": "Ticketmaster",
      "id": "LvZ18QauHDVGycYZvL5hE"
    },
    {
      "artist": "Air",
      "name": "Private Hire Igloos with thanks to Air Canada",
      "venue": "Battersea Power Station",
      "city": "London",
      "country": "Great Britain",
      "country_code": "GB",
      "date": "2025-11-09",
      "time": "21:00:00",
      "url": "https://www.universe.com/events/private-hire-igloos-with-thanks-to-air-canada-tickets-V8T3ZB?ref=ticketmaster",
      "source": "Ticketmaster",
      "id": "LvZ18QauHDVGycYZvL5hI"
    },
    {
      "artist": "Air",
      "name": "Private Hire Igloos with thanks to Air Canada",
      "venue": "Battersea Power Station",
      "city": "London",
      "country": "Great Britain",
      "country_code": "GB",
      "date": "2025-11-10",
      "time": "10:00:00",
      "url": "https://www.universe.com/events/private-hire-igloos-with-thanks-to-air-canada-tickets-V8T3ZB?ref=ticketmaster",
      "source": "Ticketmaster",
      "id": "LvZ18QauHDVGycYZvL5ht"
    },
    {
      "artist": "Air",
      "name": "Private Hire Igloos with thanks to Air Canada",
      "venue": "Battersea Power Station",
      "city": "London",
      "country": "Great Britain",
      "country_code": "GB",
      "date": "2025-11-10",
      "time": "11:00:00",
      "url": "https://www.universe.com/events/private-hire-igloos-with-thanks-to-air-canada-tickets-V8T3ZB?ref=ticketmaster",
      "source": "Ticketmaster",
      "id": "LvZ18QauHDVGycYZvL5hn"
    },
    {
      "artist": "Air",
      "name": "Private Hire Igloos with thanks to Air Canada",
      "venue": "Battersea Power Station",
      "city": "London",
      "country": "Great Britain",
      "country_code": "GB",
      "date": "2025-11-10",
      "time": "12:00:00",
      "url": "https://www.universe.com/events/private-hire-igloos-with-thanks-to-air-canada-tickets-V8T3ZB?ref=ticketmaster",
      "source": "Ticketmaster",
      "id": "LvZ18QauHDVGycYZvL5hl"
    },
    {
      "artist": "Air",
      "name": "Private Hire Igloos with thanks to Air Canada",
      "venue": "Battersea Power Station",
      "city": "London",
      "country": "Great Britain",
      "country_code": "GB",
      "date": "2025-11-10",
      "time": "13:00:00",
      "url": "https://www.universe.com/events/private-hire-igloos-with-thanks-to-air-canada-tickets-V8T3ZB?ref=ticketmaster",
      "source": "Ticketmaster",
      "id": "LvZ18QauHDVGycYZvL5hi"
    },
    {
      "artist": "Air",
      "name": "Private Hire Igloos with thanks to Air Canada",
      "venue": "Battersea Power Station",
      "city": "London",
      "country": "Great Britain",
      "country_code": "GB",
      "date": "2025-11-10",
      "time": "14:00:00",
      "url": "https://www.universe.com/events/private-hire-igloos-with-thanks-to-air-canada-tickets-V8T3ZB?ref=ticketmaster",
      "source": "Ticketmaster",
      "id": "LvZ18QauHDVGycYZvL5hc"
    },
    {
      "artist": "Air",
      "name": "Private Hire Igloos with thanks to Air Canada",
      "venue": "Battersea Power Station",
      "city": "London",
      "country": "Great Britain",
      "country_code": "GB",
      "date": "2025-11-10",
      "time": "15:00:00",
      "url": "https://www.universe.com/events/private-hire-igloos-with-thanks-to-air-canada-tickets-V8T3ZB?ref=ticketmaster",
      "source": "Ticketmaster",
      "id": "LvZ18QauHDVGycYZvL5hm"
    },
    {
      "artist": "Air",
      "name": "Private Hire Igloos with thanks to Air Canada",
      "venue": "Battersea Power Station",
      "city": "London",
      "country": "Great Britain",
      "country_code": "GB",
      "date": "2025-11-10",
      "time": "16:00:00",
      "url": "https://www.universe.com/events/private-hire-igloos-with-thanks-to-air-canada-tickets-V8T3ZB?ref=ticketmaster",
      "source": "Ticketmaster",
      "id": "LvZ18QauHDVGycYZvL5hR"
    },
    {
      "artist": "Air",
      "name": "Private Hire Igloos with thanks to Air Canada",
      "venue": "Battersea Power Station",
      "city": "London",
      "country": "Great Britain",
      "country_code": "GB",
      "date": "2025-11-10",
      "time": "17:00:00",
      "url": "https://www.universe.com/events/private-hire-igloos-with-thanks-to-air-canada-tickets-V8T3ZB?ref=ticketmaster",
      "source": "Ticketmaster",
      "id": "LvZ18QauHDVGycYZvL5hY"
    },
    {
      "artist": "Air",
      "name": "Private Hire Igloos with thanks to Air Canada",
      "venue": "Battersea Power Station",
      "city": "London",
      "country": "Great Britain",
      "country_code": "GB",
      "date": "2025-11-10",
      "time": "18:00:00",
      "url": "https://www.universe.com/events/private-hire-igloos-with-thanks-to-air-canada-tickets-V8T3ZB?ref=ticketmaster",
      "source": "Ticketmaster",
      "id": "LvZ18QauHDVGycYZvL5hs"
    },
    {
      "artist": "Air",
      "name": "Private Hire Igloos with thanks to Air Canada",
      "venue": "Battersea Power Station",
      "city": "London",
      "country": "Great Britain",
      "country_code": "GB",
      "date": "2025-11-10",
      "time": "19:00:00",
      "url": "https://www.universe.com/events/private-hire-igloos-with-thanks-to-air-canada-tickets-V8T3ZB?ref=ticketmaster",
      "source": "Ticketmaster",
      "id": "LvZ18QauHDVGycYZvL5hw"
    },
    {
      "artist": "Air",
      "name": "Private Hire Igloos with thanks to Air Canada",
      "venue": "Battersea Power Station",
      "city": "London",
      "country": "Great Britain",
      "country_code": "GB",
      "date": "2025-11-10",
      "time": "20:00:00",
      "url": "https://www.universe.com/events/private-hire-igloos-with-thanks-to-air-canada-tickets-V8T3ZB?ref=ticketmaster",
      "source": "Ticketmaster",
      "id": "LvZ18QauHDVGycYZvL5hS"
    },
    {
      "artist": "Air",
      "name": "Private Hire Igloos with thanks to Air Canada",
      "venue": "Battersea Power Station",
      "city": "London",
      "country": "Great Britain",
      "country_code": "GB",
      "date": "2025-11-10",
      "time": "21:00:00",
      "url": "https://www.universe.com/events/private-hire-igloos-with-thanks-to-air-canada-tickets-V8T3ZB?ref=ticketmaster",
      "source": "Ticketmaster",
      "id": "LvZ18QauHDVGycYZvL5hV"
    },
    {
      "artist": "Air",
      "name": "Avatar: The Last Airbender in Concert - The 20th Anniversary Tour",
      "venue": "Cal Coast Credit Union Open Air Theatre at SDSU",
      "city": "San Diego",
      "country": "United States Of America",
      "country_code": "US",
      "date": "2025-11-10",
      "time": "19:30:00",
      "url": "https://www.ticketmaster.com/avatar-the-last-airbender-in-concert-san-diego-california-11-10-2025/event/0A006299026860DB",
      "source": "Ticketmaster",
      "id": "vvG1IZbt0eQkdh"
    },
    {
      "artist": "Air",
      "name": "Private Hire Igloos with thanks to Air Canada",
      "venue": "Battersea Power Station",
      "city": "London",
      "country": "Great Britain",
      "country_code": "GB",
      "date": "2025-11-11",
      "time": "10:00:00",
      "url": "https://www.universe.com/events/private-hire-igloos-with-thanks-to-air-canada-tickets-V8T3ZB?ref=ticketmaster",
      "source": "Ticketmaster",
      "id": "LvZ18QauHDVGycYZvL5hg"
    },
    {
      "artist": "Air",
      "name": "Private Hire Igloos with thanks to Air Canada",
      "venue": "Battersea Power Station",
      "city": "London",
      "country": "Great Britain",
      "country_code": "GB",
      "date": "2025-11-11",
      "time": "11:00:00",
      "url": "https://www.universe.com/events/private-hire-igloos-with-thanks-to-air-canada-tickets-V8T3ZB?ref=ticketmaster",
      "source": "Ticketmaster",
      "id": "LvZ18QauHDVGycYZvL5hU"
    },
    {
      "artist": "Air",
      "name": "Private Hire Igloos with thanks to Air Canada",
      "venue": "Battersea Power Station",
      "city": "London",
      "country": "Great Britain",
      "country_code": "GB",
      "date": "2025-11-11",
      "time": "12:00:00",
      "url": "https://www.universe.com/events/private-hire-igloos-with-thanks-to-air-canada-tickets-V8T3ZB?ref=ticketmaster",
      "source": "Ticketmaster",
      "id": "LvZ18QauHDVGycYZvL5hM"
    },
    {
      "artist": "Air",
      "name": "Private Hire Igloos with thanks to Air Canada",
      "venue": "Battersea Power Station",
      "city": "London",
      "country": "Great Britain",
      "country_code": "GB",
      "date": "2025-11-11",
      "time": "13:00:00",
      "url": "https://www.universe.com/events/private-hire-igloos-with-thanks-to-air-canada-tickets-V8T3ZB?ref=ticketmaster",
      "source": "Ticketmaster",
      "id": "LvZ18QauHDVGycYZvL5hz"
    },
    {
      "artist": "Air",
      "name": "Private Hire Igloos with thanks to Air Canada",
      "venue": "Battersea Power Station",
      "city": "London",
      "country": "Great Britain",
      "country_code": "GB",
      "date": "2025-11-11",
      "time": "14:00:00",
      "url": "https://www.universe.com/events/private-hire-igloos-with-thanks-to-air-canada-tickets-V8T3ZB?ref=ticketmaster",
      "source": "Ticketmaster",
      "id": "LvZ18QauHDVGycYZvL5hy"
    },
    {
      "artist": "Air",
      "name": "Private Hire Igloos with thanks to Air Canada",
      "venue": "Battersea Power Station",
      "city": "London",
      "country": "Great Britain",
      "country_code": "GB",
      "date": "2025-11-11",
      "time": "15:00:00",
      "url": "https://www.universe.com/events/private-hire-igloos-with-thanks-to-air-canada-tickets-V8T3ZB?ref=ticketmaster",
      "source": "Ticketmaster",
      "id": "LvZ18QauHDVGycYZvL5hB"
    },
    {
      "artist": "Air",
      "name": "Private Hire Igloos with thanks to Air Canada",
      "venue": "Battersea Power Station",
      "city": "London",
      "country": "Great Britain",
      "country_code": "GB",
      "date": "2025-11-11",
      "time": "16:00:00",
      "url": "https://www.universe.com/events/private-hire-igloos-with-thanks-to-air-canada-tickets-V8T3ZB?ref=ticketmaster",
      "source": "Ticketmaster",
      "id": "LvZ18QauHDVGycYZvL5hD"
    },
    {
      "artist": "Air",
      "name": "Private Hire Igloos with thanks to Air Canada",
      "venue": "Battersea Power Station",
      "city": "London",
      "country": "Great Britain",
      "country_code": "GB",
      "date": "2025-11-11",
      "time": "17:00:00",
      "url": "https://www.universe.com/events/private-hire-igloos-with-thanks-to-air-canada-tickets-V8T3ZB?ref=ticketmaster",
      "source": "Ticketmaster",
      "id": "LvZ18QauHDVGycYZvL5hH"
    },
    {
      "artist": "Air",
      "name": "Private Hire Igloos with thanks to Air Canada",
      "venue": "Battersea Power Station",
      "city": "London",
      "country": "Great Britain",
      "country_code": "GB",
      "date": "2025-11-11",
      "time": "18:00:00",
      "url": "https://www.universe.com/events/private-hire-igloos-with-thanks-to-air-canada-tickets-V8T3ZB?ref=ticketmaster",
      "source": "Ticketmaster",
      "id": "LvZ18QauHDVGycYZvL5hW"
    },
    {
      "artist": "Air",
      "name": "Private Hire Igloos with thanks to Air Canada",
      "venue": "Battersea Power Station",
      "city": "London",
      "country": "Great Britain",
      "country_code": "GB",
      "date": "2025-11-11",
      "time": "19:00:00",
      "url": "https://www.universe.com/events/private-hire-igloos-with-thanks-to-air-canada-tickets-V8T3ZB?ref=ticketmaster",
      "source": "Ticketmaster",
      "id": "LvZ18QauHDVGycYZvL5hX"
    },
    {
      "artist": "Air",
      "name": "Esprit D'Air: Manchester",
      "venue": "Rebellion Manchester",
      "city": "Manchester",
      "country": "Great Britain",
      "country_code": "GB",
      "date": "2025-11-11",
      "time": "19:00:00",
      "url": "https://www.universe.com/events/esprit-dair-manchester-tickets-6G18LW?ref=ticketmaster",
      "source": "Ticketmaster",
      "id": "LvZ18QkfzOLQKJvskAaDp"
    },
    {
      "artist": "Air",
      "name": "Private Hire Igloos with thanks to Air Canada",
      "venue": "Battersea Power Station",
      "city": "London",
      "country": "Great Britain",
      "country_code": "GB",
      "date": "2025-11-11",
      "time": "20:00:00",
      "url": "https://www.universe.com/events/private-hire-igloos-with-thanks-to-air-canada-tickets-V8T3ZB?ref=ticketmaster",
      "source": "Ticketmaster",
      "id": "LvZ18QauHDVGycYZvL5hT"
    },
    {
      "artist": "Air",
      "name": "Private Hire Igloos with thanks to Air Canada",
      "venue": "Battersea Power Station",
      "city": "London",
      "country": "Great Britain",
      "country_code": "GB",
      "date": "2025-11-11",
      "time": "21:00:00",
      "url": "https://www.universe.com/events/private-hire-igloos-with-thanks-to-air-canada-tickets-V8T3ZB?ref=ticketmaster",
      "source": "Ticketmaster",
      "id": "LvZ18QauHDVGycYZvL5jZ"
    },
    {
      "artist": "Air",
      "name": "Air Force Academy Falcons Mens Basketball vs. LIU Sharks Mens Basketball",
      "venue": "Clune Arena",
      "city": "USAF Academy",
      "country": "United States Of America",
      "country_code": "US",
      "date": "2025-11-11",
      "time": "14:00:00",
      "url": "https://www.ticketmaster.com/event/Z7r9jZ1A7j3u7",
      "source": "Ticketmaster",
      "id": "Z7r9jZ1A7j3u7"
    },
    {
      "artist": "Air",
      "name": "Private Hire Igloos with thanks to Air Canada",
      "venue": "Battersea Power Station",
      "city": "London",
      "country": "Great Britain",
      "country_code": "GB",
      "date": "2025-11-12",
      "time": "10:00:00",
      "url": "https://www.universe.com/events/private-hire-igloos-with-thanks-to-air-canada-tickets-V8T3ZB?ref=ticketmaster",
      "source": "Ticketmaster",
      "id": "LvZ18QauHDVGycYZvL5jv"
    },
    {
      "artist": "Air",
      "name": "Private Hire Igloos with thanks to Air Canada",
      "venue": "Battersea Power Station",
      "city": "London",
      "country": "Great Britain",
      "country_code": "GB",
      "date": "2025-11-12",
      "time": "11:00:00",
      "url": "https://www.universe.com/events/private-hire-igloos-with-thanks-to-air-canada-tickets-V8T3ZB?ref=ticketmaster",
      "source": "Ticketmaster",
      "id": "LvZ18QauHDVGycYZvL5je"
    },
    {
      "artist": "Air",
      "name": "Private Hire Igloos with thanks to Air Canada",
      "venue": "Battersea Power Station",
      "city": "London",
      "country": "Great Britain",
      "country_code": "GB",
      "date": "2025-11-12",
      "time": "12:00:00",
      "url": "https://www.universe.com/events/private-hire-igloos-with-thanks-to-air-canada-tickets-V8T3ZB?ref=ticketmaster",
      "source": "Ticketmaster",
      "id": "LvZ18QauHDVGycYZvL5jd"
    },
    {
      "artist": "Air",
      "name": "Private Hire Igloos with thanks to Air Canada",
      "venue": "Battersea Power Station",
      "city": "London",
      "country": "Great Britain",
      "country_code": "GB",
      "date": "2025-11-12",
      "time": "13:00:00",
      "url": "https://www.universe.com/events/private-hire-igloos-with-thanks-to-air-canada-tickets-V8T3ZB?ref=ticketmaster",
      "source": "Ticketmaster",
      "id": "LvZ18QauHDVGycYZvL5j7"
    },
    {
      "artist": "Air",
      "name": "Private Hire Igloos with thanks to Air Canada",
      "venue": "Battersea Power Station",
      "city": "London",
      "country": "Great Britain",
      "country_code": "GB",
      "date": "2025-11-12",
      "time": "14:00:00",
      "url": "https://www.universe.com/events/private-hire-igloos-with-thanks-to-air-canada-tickets-V8T3ZB?ref=ticketmaster",
      "source": "Ticketmaster",
      "id": "LvZ18QauHDVGycYZvL5jA"
    },
    {
      "artist": "Air",
      "name": "Private Hire Igloos with thanks to Air Canada",
      "venue": "Battersea Power Station",
      "city": "London",
      "country": "Great Britain",
      "country_code": "GB",
      "date": "2025-11-12",
      "time": "15:00:00",
      "url": "https://www.universe.com/events/private-hire-igloos-with-thanks-to-air-canada-tickets-V8T3ZB?ref=ticketmaster",
      "source": "Ticketmaster",
      "id": "LvZ18QauHDVGycYZvL5jk"
    },
    {
      "artist": "Air",
      "name": "Private Hire Igloos with thanks to Air Canada",
      "venue": "Battersea Power Station",
      "city": "London",
      "country": "Great Britain",
      "country_code": "GB",
      "date": "2025-11-12",
      "time": "16:00:00",
      "url": "https://www.universe.com/events/private-hire-igloos-with-thanks-to-air-canada-tickets-V8T3ZB?ref=ticketmaster",
      "source": "Ticketmaster",
      "id": "LvZ18QauHDVGycYZvL5j6"
    },
    {
      "artist": "Air",
      "name": "Private Hire Igloos with thanks to Air Canada",
      "venue": "Battersea Power Station",
      "city": "London",
      "country": "Great Britain",
      "country_code": "GB",
      "date": "2025-11-12",
      "time": "17:00:00",
      "url": "https://www.universe.com/events/private-hire-igloos-with-thanks-to-air-canada-tickets-V8T3ZB?ref=ticketmaster",
      "source": "Ticketmaster",
      "id": "LvZ18QauHDVGycYZvL5jF"
    },
    {
      "artist": "Air",
      "name": "Private Hire Igloos with thanks to Air Canada",
      "venue": "Battersea Power Station",
      "city": "London",
      "country": "Great Britain",
      "country_code": "GB",
      "date": "2025-11-12",
      "time": "18:00:00",
      "url": "https://www.universe.com/events/private-hire-igloos-with-thanks-to-air-canada-tickets-V8T3ZB?ref=ticketmaster",
      "source": "Ticketmaster",
      "id": "LvZ18QauHDVGycYZvL5ja"
    },
    {
      "artist": "Air",
      "name": "Esprit D'Air",
      "venue": "KK's Steel Mill",
      "city": "Wolverhampton",
      "country": "Great Britain",
      "country_code": "GB",
      "date": "2025-11-12",
      "time": "19:00:00",
      "url": "https://www.ticketweb.uk/event/esprit-dair-kks-steel-mill-tickets/13871234?REFERRAL_ID=tmfeed",
      "source": "Ticketmaster",
      "id": "17GOvxG6CEWD-jb"
    },
    {
      "artist": "Air",
      "name": "Private Hire Igloos with thanks to Air Canada",
      "venue": "Battersea Power Station",
      "city": "London",
      "country": "Great Britain",
      "country_code": "GB",
      "date": "2025-11-12",
      "time": "19:00:00",
      "url": "https://www.universe.com/events/private-hire-igloos-with-thanks-to-air-canada-tickets-V8T3ZB?ref=ticketmaster",
      "source": "Ticketmaster",
      "id": "LvZ18QauHDVGycYZvL5j1"
    },
    {
      "artist": "Air",
      "name": "Esprit D'Air: Wolverhampton",
      "venue": "KK's Steel Mill",
      "city": "Wolverhampton",
      "country": "Great Britain",
      "country_code": "GB",
      "date": "2025-11-12",
      "time": "19:00:00",
      "url": "https://www.universe.com/events/esprit-dair-wolverhampton-tickets-H38FP6?ref=ticketmaster",
      "source": "Ticketmaster",
      "id": "LvZ18QkpvmGO4cZZ0jfzM"
    },
    {
      "artist": "Air",
      "name": "Private Hire Igloos with thanks to Air Canada",
      "venue": "Battersea Power Station",
      "city": "London",
      "country": "Great Britain",
      "country_code": "GB",
      "date": "2025-11-12",
      "time": "20:00:00",
      "url": "https://www.universe.com/events/private-hire-igloos-with-thanks-to-air-canada-tickets-V8T3ZB?ref=ticketmaster",
      "source": "Ticketmaster",
      "id": "LvZ18QauHDVGycYZvL5j5"
    },
    {
      "artist": "Air",
      "name": "Private Hire Igloos with thanks to Air Canada",
      "venue": "Battersea Power Station",
      "city": "London",
      "country": "Great Britain",
      "country_code": "GB",
      "date": "2025-11-12",
      "time": "21:00:00",
      "url": "https://www.universe.com/events/private-hire-igloos-with-thanks-to-air-canada-tickets-V8T3ZB?ref=ticketmaster",
      "source": "Ticketmaster",
      "id": "LvZ18QauHDVGycYZvL5jG"
    },
    {
      "artist": "Air",
      "name": "Zakk Sabbath",
      "venue": "Val Air Ballroom",
      "city": "West Des Moines",
      "country": "United States Of America",
      "country_code": "US",
      "date": "2025-11-12",
      "time": "19:00:00",
      "url": "https://www.ticketmaster.com/event/Z7r9jZ1A7_UG4",
      "source": "Ticketmaster",
      "id": "Z7r9jZ1A7_UG4"
    },
    {
      "artist": "Air",
      "name": "Private Hire Igloos with thanks to Air Canada",
      "venue": "Battersea Power Station",
      "city": "London",
      "country": "Great Britain",
      "country_code": "GB",
      "date": "2025-11-13",
      "time": "10:00:00",
      "url": "https://www.universe.com/events/private-hire-igloos-with-thanks-to-air-canada-tickets-V8T3ZB?ref=ticketmaster",
      "source": "Ticketmaster",
      "id": "LvZ18QauHDVGycYZvL5ju"
    },
    {
      "artist": "Air",
      "name": "Private Hire Igloos with thanks to Air Canada",
      "venue": "Battersea Power Station",
      "city": "London",
      "country": "Great Britain",
      "country_code": "GB",
      "date": "2025-11-13",
      "time": "11:00:00",
      "url": "https://www.universe.com/events/private-hire-igloos-with-thanks-to-air-canada-tickets-V8T3ZB?ref=ticketmaster",
      "source": "Ticketmaster",
      "id": "LvZ18QauHDVGycYZvL5jC"
    },
    {
      "artist": "Air",
      "name": "Private Hire Igloos with thanks to Air Canada",
      "venue": "Battersea Power Station",
      "city": "London",
      "country": "Great Britain",
      "country_code": "GB",
      "date": "2025-11-13",
      "time": "12:00:00",
      "url": "https://www.universe.com/events/private-hire-igloos-with-thanks-to-air-canada-tickets-V8T3ZB?ref=ticketmaster",
      "source": "Ticketmaster",
      "id": "LvZ18QauHDVGycYZvL5j2"
    },
    {
      "artist": "Air",
      "name": "Private Hire Igloos with thanks to Air Canada",
      "venue": "Battersea Power Station",
      "city": "London",
      "country": "Great Britain",
      "country_code": "GB",
      "date": "2025-11-13",
      "time": "13:00:00",
      "url": "https://www.universe.com/events/private-hire-igloos-with-thanks-to-air-canada-tickets-V8T3ZB?ref=ticketmaster",
      "source": "Ticketmaster",
      "id": "LvZ18QauHDVGycYZvL5j8"
    },
    {
      "artist": "Air",
      "name": "Private Hire Igloos with thanks to Air Canada",
      "venue": "Battersea Power Station",
      "city": "London",
      "country": "Great Britain",
      "country_code": "GB",
      "date": "2025-11-13",
      "time": "14:00:00",
      "url": "https://www.universe.com/events/private-hire-igloos-with-thanks-to-air-canada-tickets-V8T3ZB?ref=ticketmaster",
      "source": "Ticketmaster",
      "id": "LvZ18QauHDVGycYZvL5jo"
    },
    {
      "artist": "Air",
      "name": "Private Hire Igloos with thanks to Air Canada",
      "venue": "Battersea Power Station",
      "city": "London",
      "country": "Great Britain",
      "country_code": "GB",
      "date": "2025-11-13",
      "time": "15:00:00",
      "url": "https://www.universe.com/events/private-hire-igloos-with-thanks-to-air-canada-tickets-V8T3ZB?ref=ticketmaster",
      "source": "Ticketmaster",
      "id": "LvZ18QauHDVGycYZvL5j3"
    },
    {
      "artist": "Air",
      "name": "Private Hire Igloos with thanks to Air Canada",
      "venue": "Battersea Power Station",
      "city": "London",
      "country": "Great Britain",
      "country_code": "GB",
      "date": "2025-11-13",
      "time": "16:00:00",
      "url": "https://www.universe.com/events/private-hire-igloos-with-thanks-to-air-canada-tickets-V8T3ZB?ref=ticketmaster",
      "source": "Ticketmaster",
      "id": "LvZ18QauHDVGycYZvL5jK"
    },
    {
      "artist": "Air",
      "name": "Private Hire Igloos with thanks to Air Canada",
      "venue": "Battersea Power Station",
      "city": "London",
      "country": "Great Britain",
      "country_code": "GB",
      "date": "2025-11-13",
      "time": "17:00:00",
      "url": "https://www.universe.com/events/private-hire-igloos-with-thanks-to-air-canada-tickets-V8T3ZB?ref=ticketmaster",
      "source": "Ticketmaster",
      "id": "LvZ18QauHDVGycYZvL5jf"
    },
    {
      "artist": "Air",
      "name": "Private Hire Igloos with thanks to Air Canada",
      "venue": "Battersea Power Station",
      "city": "London",
      "country": "Great Britain",
      "country_code": "GB",
      "date": "2025-11-13",
      "time": "18:00:00",
      "url": "https://www.universe.com/events/private-hire-igloos-with-thanks-to-air-canada-tickets-V8T3ZB?ref=ticketmaster",
      "source": "Ticketmaster",
      "id": "LvZ18QauHDVGycYZvL5j4"
    },
    {
      "artist": "Air",
      "name": "Curved Air",
      "venue": "229",
      "city": "London",
      "country": "Great Britain",
      "country_code": "GB",
      "date": "2025-11-13",
      "time": "19:00:00",
      "url": "https://www.ticketweb.uk/event/curved-air-229-tickets/13980793?REFERRAL_ID=tmfeed",
      "source": "Ticketmaster",
      "id": "1AdFZbpGkSM6vHW"
    },
    {
      "artist": "Air",
      "name": "Private Hire Igloos with thanks to Air Canada",
      "venue": "Battersea Power Station",
      "city": "London",
      "country": "Great Britain",
      "country_code": "GB",
      "date": "2025-11-13",
      "time": "19:00:00",
      "url": "https://www.universe.com/events/private-hire-igloos-with-thanks-to-air-canada-tickets-V8T3ZB?ref=ticketmaster",
      "source": "Ticketmaster",
      "id": "LvZ18QauHDVGycYZvL5jp"
    },
    {
      "artist": "Air",
      "name": "Esprit D'Air: Swansea",
      "venue": "Hangar 18",
      "city": "Swansea ",
      "country": "Great Britain",
      "country_code": "GB",
      "date": "2025-11-13",
      "time": "19:00:00",
      "url": "https://www.universe.com/events/esprit-dair-swansea-tickets-LV8B63?ref=ticketmaster",
      "source": "Ticketmaster",
      "id": "LvZ18Qkpd-ng7TOZ0LL9t"
    },
    {
      "artist": "Air",
      "name": "Private Hire Igloos with thanks to Air Canada",
      "venue": "Battersea Power Station",
      "city": "London",
      "country": "Great Britain",
      "country_code": "GB",
      "date": "2025-11-13",
      "time": "20:00:00",
      "url": "https://www.universe.com/events/private-hire-igloos-with-thanks-to-air-canada-tickets-V8T3ZB?ref=ticketmaster",
      "source": "Ticketmaster",
      "id": "LvZ18QauHDVGycYZvL5j9"
    },
    {
      "artist": "Air",
      "name": "Private Hire Igloos with thanks to Air Canada",
      "venue": "Battersea Power Station",
      "city": "London",
      "country": "Great Britain",
      "country_code": "GB",
      "date": "2025-11-13",
      "time": "21:00:00",
      "url": "https://www.universe.com/events/private-hire-igloos-with-thanks-to-air-canada-tickets-V8T3ZB?ref=ticketmaster",
      "source": "Ticketmaster",
      "id": "LvZ18QauHDVGycYZvL5jb"
    },
    {
      "artist": "Air",
      "name": "ACC Men's Soccer Semi-Finals",
      "venue": "WakeMed Soccer Park",
      "city": "Cary",
      "country": "United States Of America",
      "country_code": "US",
      "date": "2025-11-13",
      "time": "17:30:00",
      "url": "",
      "source": "Ticketmaster",
      "id": "Za5ju3rKuqZDd9ARoQBntul1Vwt2kJM3zu"
    },
    {
      "artist": "Air",
      "name": "Air Force Academy Falcons Hockey vs. Holy Cross Crusaders Hockey",
      "venue": "Cadet Ice Arena",
      "city": "USAF Academy",
      "country": "United States Of America",
      "country_code": "US",
      "date": "2025-11-14",
      "time": "",
      "url": "https://www.ticketmaster.com/event/Z7r9jZ1A7_IFz",
      "source": "Ticketmaster",
      "id": "Z7r9jZ1A7_IFz"
    },
    {
      "artist": "Air",
      "name": "Private Hire Igloos with thanks to Air Canada",
      "venue": "Battersea Power Station",
      "city": "London",
      "country": "Great Britain",
      "country_code": "GB",
      "date": "2025-11-14",
      "time": "10:00:00",
      "url": "https://www.universe.com/events/private-hire-igloos-with-thanks-to-air-canada-tickets-V8T3ZB?ref=ticketmaster",
      "source": "Ticketmaster",
      "id": "LvZ18QauHDVGycYZvL5j_"
    },
    {
      "artist": "Air",
      "name": "Private Hire Igloos with thanks to Air Canada",
      "venue": "Battersea Power Station",
      "city": "London",
      "country": "Great Britain",
      "country_code": "GB",
      "date": "2025-11-14",
      "time": "11:00:00",
      "url": "https://www.universe.com/events/private-hire-igloos-with-thanks-to-air-canada-tickets-V8T3ZB?ref=ticketmaster",
      "source": "Ticketmaster",
      "id": "LvZ18QauHDVGycYZvL5jQ"
    },
    {
      "artist": "Air",
      "name": "Private Hire Igloos with thanks to Air Canada",
      "venue": "Battersea Power Station",
      "city": "London",
      "country": "Great Britain",
      "country_code": "GB",
      "date": "2025-11-14",
      "time": "12:00:00",
      "url": "https://www.universe.com/events/private-hire-igloos-with-thanks-to-air-canada-tickets-V8T3ZB?ref=ticketmaster",
      "source": "Ticketmaster",
      "id": "LvZ18QauHDVGycYZvL5jh"
    },
    {
      "artist": "Air",
      "name": "Private Hire Igloos with thanks to Air Canada",
      "venue": "Battersea Power Station",
      "city": "London",
      "country": "Great Britain",
      "country_code": "GB",
      "date": "2025-11-14",
      "time": "13:00:00",
      "url": "https://www.universe.com/events/private-hire-igloos-with-thanks-to-air-canada-tickets-V8T3ZB?ref=ticketmaster",
      "source": "Ticketmaster",
      "id": "LvZ18QauHDVGycYZvL5jj"
    },
    {
      "artist": "Air",
      "name": "Private Hire Igloos with thanks to Air Canada",
      "venue": "Battersea Power Station",
      "city": "London",
      "country": "Great Britain",
      "country_code": "GB",
      "date": "2025-11-14",
      "time": "14:00:00",
      "url": "https://www.universe.com/events/private-hire-igloos-with-thanks-to-air-canada-tickets-V8T3ZB?ref=ticketmaster",
      "source": "Ticketmaster",
      "id": "LvZ18QauHDVGycYZvL5jq"
    },
    {
      "artist": "Air",
      "name": "Private Hire Igloos with thanks to Air Canada",
      "venue": "Battersea Power Station",
      "city": "London",
      "country": "Great Britain",
      "country_code": "GB",
      "date": "2025-11-14",
      "time": "15:00:00",
      "url": "https://www.universe.com/events/private-hire-igloos-with-thanks-to-air-canada-tickets-V8T3ZB?ref=ticketmaster",
      "source": "Ticketmaster",
      "id": "LvZ18QauHDVGycYZvL5jr"
    },
    {
      "artist": "Air",
      "name": "Private Hire Igloos with thanks to Air Canada",
      "venue": "Battersea Power Station",
      "city": "London",
      "country": "Great Britain",
      "country_code": "GB",
      "date": "2025-11-14",
      "time": "16:00:00",
      "url": "https://www.universe.com/events/private-hire-igloos-with-thanks-to-air-canada-tickets-V8T3ZB?ref=ticketmaster",
      "source": "Ticketmaster",
      "id": "LvZ18QauHDVGycYZvL5jL"
    },
    {
      "artist": "Air",
      "name": "Private Hire Igloos with thanks to Air Canada",
      "venue": "Battersea Power Station",
      "city": "London",
      "country": "Great Britain",
      "country_code": "GB",
      "date": "2025-11-14",
      "time": "17:00:00",
      "url": "https://www.universe.com/events/private-hire-igloos-with-thanks-to-air-canada-tickets-V8T3ZB?ref=ticketmaster",
      "source": "Ticketmaster",
      "id": "LvZ18QauHDVGycYZvL5jO"
    },
    {
      "artist": "Air",
      "name": "Private Hire Igloos with thanks to Air Canada",
      "venue": "Battersea Power Station",
      "city": "London",
      "country": "Great Britain",
      "country_code": "GB",
      "date": "2025-11-14",
      "time": "18:00:00",
      "url": "https://www.universe.com/events/private-hire-igloos-with-thanks-to-air-canada-tickets-V8T3ZB?ref=ticketmaster",
      "source": "Ticketmaster",
      "id": "LvZ18QauHDVGycYZvL5j-"
    },
    {
      "artist": "Air",
      "name": "90lar Kafası - Nihat Sırdar",
      "venue": "Antalya Open Air",
      "city": "Antalya",
      "country": "Turkey",
      "country_code": "TR",
      "date": "2025-11-14",
      "time": "21:00:00",
      "url": "https://www.biletix.com/performance/41968/001/TURKIYE/tr",
      "source": "Ticketmaster",
      "id": "Z6HyzZyMZ1kvvPIZv"
    },
    {
      "artist": "Air",
      "name": "Private Hire Igloos with thanks to Air Canada",
      "venue": "Battersea Power Station",
      "city": "London",
      "country": "Great Britain",
      "country_code": "GB",
      "date": "2025-11-14",
      "time": "19:00:00",
      "url": "https://www.universe.com/events/private-hire-igloos-with-thanks-to-air-canada-tickets-V8T3ZB?ref=ticketmaster",
      "source": "Ticketmaster",
      "id": "LvZ18QauHDVGycYZvL5jx"
    },
    {
      "artist": "Air",
      "name": "Esprit D'Air: York",
      "venue": "The Crescent",
      "city": "York",
      "country": "Great Britain",
      "country_code": "GB",
      "date": "2025-11-14",
      "time": "19:30:00",
      "url": "https://www.universe.com/events/esprit-dair-york-tickets-VDPQFN?ref=ticketmaster",
      "source": "Ticketmaster",
      "id": "LvZ18Qkp7FUSWg8Zl_KvE"
    },
    {
      "artist": "Air",
      "name": "Private Hire Igloos with thanks to Air Canada",
      "venue": "Battersea Power Station",
      "city": "London",
      "country": "Great Britain",
      "country_code": "GB",
      "date": "2025-11-14",
      "time": "20:00:00",
      "url": "https://www.universe.com/events/private-hire-igloos-with-thanks-to-air-canada-tickets-V8T3ZB?ref=ticketmaster",
      "source": "Ticketmaster",
      "id": "LvZ18QauHDVGycYZvL5jN"
    },
    {
      "artist": "Air",
      "name": "Private Hire Igloos with thanks to Air Canada",
      "venue": "Battersea Power Station",
      "city": "London",
      "country": "Great Britain",
      "country_code": "GB",
      "date": "2025-11-14",
      "time": "21:00:00",
      "url": "https://www.universe.com/events/private-hire-igloos-with-thanks-to-air-canada-tickets-V8T3ZB?ref=ticketmaster",
      "source": "Ticketmaster",
      "id": "LvZ18QauHDVGycYZvL5j0"
    },
    {
      "artist": "Air",
      "name": "Deck the Diamond",
      "venue": "Day Air Ballpark",
      "city": "Dayton",
      "country": "United States Of America",
      "country_code": "US",
      "date": "2025-11-14",
      "time": "18:00:00",
      "url": "https://www.ticketmaster.com/deck-the-diamond-dayton-ohio-11-14-2025/event/160062E99DBD2B42",
      "source": "Ticketmaster",
      "id": "17AOvxG6CJqR3ce"
    },
    {
      "artist": "Air",
      "name": "Air Force Academy Falcons Hockey vs. Holy Cross Crusaders Hockey",
      "venue": "Cadet Ice Arena",
      "city": "USAF Academy",
      "country": "United States Of America",
      "country_code": "US",
      "date": "2025-11-15",
      "time": "",
      "url": "https://www.ticketmaster.com/event/Z7r9jZ1A7_IFy",
      "source": "Ticketmaster",
      "id": "Z7r9jZ1A7_IFy"
    },
    {
      "artist": "Air",
      "name": "Du Haut des Airs Canada",
      "venue": "Salle Claude-Léveillée",
      "city": "Montreal",
      "country": "Can",
      "country_code": "CAN",
      "date": "2025-11-14",
      "time": "20:00:00",
      "url": "",
      "source": "Ticketmaster",
      "id": "Za5ju3rKuqZDdkpf9DiQvCHtZ60r7zaVl5"
    },
    {
      "artist": "Air",
      "name": "Private Hire Igloos with thanks to Air Canada",
      "venue": "Battersea Power Station",
      "city": "London",
      "country": "Great Britain",
      "country_code": "GB",
      "date": "2025-11-15",
      "time": "10:00:00",
      "url": "https://www.universe.com/events/private-hire-igloos-with-thanks-to-air-canada-tickets-V8T3ZB?ref=ticketmaster",
      "source": "Ticketmaster",
      "id": "LvZ18QauHDVGycYZvL5jP"
    },
    {
      "artist": "Air",
      "name": "Private Hire Igloos with thanks to Air Canada",
      "venue": "Battersea Power Station",
      "city": "London",
      "country": "Great Britain",
      "country_code": "GB",
      "date": "2025-11-15",
      "time": "11:00:00",
      "url": "https://www.universe.com/events/private-hire-igloos-with-thanks-to-air-canada-tickets-V8T3ZB?ref=ticketmaster",
      "source": "Ticketmaster",
      "id": "LvZ18QauHDVGycYZvL5jJ"
    },
    {
      "artist": "Air",
      "name": "Private Hire Igloos with thanks to Air Canada",
      "venue": "Battersea Power Station",
      "city": "London",
      "country": "Great Britain",
      "country_code": "GB",
      "date": "2025-11-15",
      "time": "12:00:00",
      "url": "https://www.universe.com/events/private-hire-igloos-with-thanks-to-air-canada-tickets-V8T3ZB?ref=ticketmaster",
      "source": "Ticketmaster",
      "id": "LvZ18QauHDVGycYZvL5jE"
    },
    {
      "artist": "Air",
      "name": "Private Hire Igloos with thanks to Air Canada",
      "venue": "Battersea Power Station",
      "city": "London",
      "country": "Great Britain",
      "country_code": "GB",
      "date": "2025-11-15",
      "time": "13:00:00",
      "url": "https://www.universe.com/events/private-hire-igloos-with-thanks-to-air-canada-tickets-V8T3ZB?ref=ticketmaster",
      "source": "Ticketmaster",
      "id": "LvZ18QauHDVGycYZvL5jI"
    },
    {
      "artist": "Air",
      "name": "Private Hire Igloos with thanks to Air Canada",
      "venue": "Battersea Power Station",
      "city": "London",
      "country": "Great Britain",
      "country_code": "GB",
      "date": "2025-11-15",
      "time": "14:00:00",
      "url": "https://www.universe.com/events/private-hire-igloos-with-thanks-to-air-canada-tickets-V8T3ZB?ref=ticketmaster",
      "source": "Ticketmaster",
      "id": "LvZ18QauHDVGycYZvL5jt"
    },
    {
      "artist": "Air",
      "name": "Private Hire Igloos with thanks to Air Canada",
      "venue": "Battersea Power Station",
      "city": "London",
      "country": "Great Britain",
      "country_code": "GB",
      "date": "2025-11-15",
      "time": "15:00:00",
      "url": "https://www.universe.com/events/private-hire-igloos-with-thanks-to-air-canada-tickets-V8T3ZB?ref=ticketmaster",
      "source": "Ticketmaster",
      "id": "LvZ18QauHDVGycYZvL5jn"
    },
    {
      "artist": "Air",
      "name": "Private Hire Igloos with thanks to Air Canada",
      "venue": "Battersea Power Station",
      "city": "London",
      "country": "Great Britain",
      "country_code": "GB",
      "date": "2025-11-15",
      "time": "16:00:00",
      "url": "https://www.universe.com/events/private-hire-igloos-with-thanks-to-air-canada-tickets-V8T3ZB?ref=ticketmaster",
      "source": "Ticketmaster",
      "id": "LvZ18QauHDVGycYZvL5jl"
    },
    {
      "artist": "Air",
      "name": "Private Hire Igloos with thanks to Air Canada",
      "venue": "Battersea Power Station",
      "city": "London",
      "country": "Great Britain",
      "country_code": "GB",
      "date": "2025-11-15",
      "time": "17:00:00",
      "url": "https://www.universe.com/events/private-hire-igloos-with-thanks-to-air-canada-tickets-V8T3ZB?ref=ticketmaster",
      "source": "Ticketmaster",
      "id": "LvZ18QauHDVGycYZvL5ji"
    },
    {
      "artist": "Air",
      "name": "UConn Huskies Football vs. Air Force Academy Falcons Football",
      "venue": "Pratt & Whitney Stadium",
      "city": "East Hartford",
      "country": "United States Of America",
      "country_code": "US",
      "date": "2025-11-15",
      "time": "12:00:00",
      "url": "https://www.ticketmaster.com/event/Z7r9jZ1A7_Nqp",
      "source": "Ticketmaster",
      "id": "Z7r9jZ1A7_Nqp"
    },
    {
      "artist": "Air",
      "name": "Private Hire Igloos with thanks to Air Canada",
      "venue": "Battersea Power Station",
      "city": "London",
      "country": "Great Britain",
      "country_code": "GB",
      "date": "2025-11-15",
      "time": "18:00:00",
      "url": "https://www.universe.com/events/private-hire-igloos-with-thanks-to-air-canada-tickets-V8T3ZB?ref=ticketmaster",
      "source": "Ticketmaster",
      "id": "LvZ18QauHDVGycYZvL5jc"
    },
    {
      "artist": "Air",
      "name": "Mabel Matiz",
      "venue": "Antalya Open Air",
      "city": "Antalya",
      "country": "Turkey",
      "country_code": "TR",
      "date": "2025-11-15",
      "time": "21:00:00",
      "url": "https://www.biletix.com/performance/4DTOI/001/TURKIYE/tr",
      "source": "Ticketmaster",
      "id": "Z2HyzZyMZACr_Kvve"
    },
    {
      "artist": "Air",
      "name": "Private Hire Igloos with thanks to Air Canada",
      "venue": "Battersea Power Station",
      "city": "London",
      "country": "Great Britain",
      "country_code": "GB",
      "date": "2025-11-15",
      "time": "19:00:00",
      "url": "https://www.universe.com/events/private-hire-igloos-with-thanks-to-air-canada-tickets-V8T3ZB?ref=ticketmaster",
      "source": "Ticketmaster",
      "id": "LvZ18QauHDVGycYZvL5jm"
    },
    {
      "artist": "Air",
      "name": "Esprit D'Air: Dunfermline",
      "venue": "P J Molloys",
      "city": "Dunfermline",
      "country": "Great Britain",
      "country_code": "GB",
      "date": "2025-11-15",
      "time": "19:00:00",
      "url": "https://www.universe.com/events/esprit-dair-dunfermline-tickets-2NMS8J?ref=ticketmaster",
      "source": "Ticketmaster",
      "id": "LvZ18Qkp7xmvx8YZlQXkI"
    },
    {
      "artist": "Air",
      "name": "Air Force Academy Falcons Mens Basketball vs. Miami of Ohio Redhawks Mens Basketball",
      "venue": "Clune Arena",
      "city": "USAF Academy",
      "country": "United States Of America",
      "country_code": "US",
      "date": "2025-11-15",
      "time": "12:00:00",
      "url": "https://www.ticketmaster.com/event/Z7r9jZ1A7j3uv",
      "source": "Ticketmaster",
      "id": "Z7r9jZ1A7j3uv"
    },
    {
      "artist": "Air",
      "name": "Private Hire Igloos with thanks to Air Canada",
      "venue": "Battersea Power Station",
      "city": "London",
      "country": "Great Britain",
      "country_code": "GB",
      "date": "2025-11-15",
      "time": "20:00:00",
      "url": "https://www.universe.com/events/private-hire-igloos-with-thanks-to-air-canada-tickets-V8T3ZB?ref=ticketmaster",
      "source": "Ticketmaster",
      "id": "LvZ18QauHDVGycYZvL5jR"
    },
    {
      "artist": "Air",
      "name": "Private Hire Igloos with thanks to Air Canada",
      "venue": "Battersea Power Station",
      "city": "London",
      "country": "Great Britain",
      "country_code": "GB",
      "date": "2025-11-15",
      "time": "21:00:00",
      "url": "https://www.universe.com/events/private-hire-igloos-with-thanks-to-air-canada-tickets-V8T3ZB?ref=ticketmaster",
      "source": "Ticketmaster",
      "id": "LvZ18QauHDVGycYZvL5jY"
    },
    {
      "artist": "Air",
      "name": "Deck the Diamond",
      "venue": "Day Air Ballpark",
      "city": "Dayton",
      "country": "United States Of America",
      "country_code": "US",
      "date": "2025-11-15",
      "time": "18:00:00",
      "url": "https://www.ticketmaster.com/deck-the-diamond-dayton-ohio-11-15-2025/event/160062E99DC12B4A",
      "source": "Ticketmaster",
      "id": "17AOvxG6CJqY3c1"
    },
    {
      "artist": "Air",
      "name": "Air Supply - 50th Anniversary Celebration",
      "venue": "Springfield Symphony Hall",
      "city": "Springfield",
      "country": "United States Of America",
      "country_code": "US",
      "date": "2025-11-15",
      "time": "20:00:00",
      "url": "https://www.ticketmaster.com/air-supply-50th-anniversary-celebration-springfield-massachusetts-11-15-2025/event/010062B3165A664B",
      "source": "Ticketmaster",
      "id": "vvG17ZblGppJ_5"
    },
    {
      "artist": "Air",
      "name": "Jose Maria Napoleon - Hasta Siempre. Tour de Despedida USA 2025",
      "venue": "Cal Coast Credit Union Open Air Theatre at SDSU",
      "city": "San Diego",
      "country": "United States Of America",
      "country_code": "US",
      "date": "2025-11-15",
      "time": "20:00:00",
      "url": "https://www.ticketmaster.com/jose-maria-napoleon-hasta-siempre-tour-san-diego-california-11-15-2025/event/0A0062988C1F3043",
      "source": "Ticketmaster",
      "id": "vvG1IZbtxG6Svd"
    },
    {
      "artist": "Air",
      "name": "Private Hire Igloos with thanks to Air Canada",
      "venue": "Battersea Power Station",
      "city": "London",
      "country": "Great Britain",
      "country_code": "GB",
      "date": "2025-11-16",
      "time": "10:00:00",
      "url": "https://www.universe.com/events/private-hire-igloos-with-thanks-to-air-canada-tickets-V8T3ZB?ref=ticketmaster",
      "source": "Ticketmaster",
      "id": "LvZ18QauHDVGycYZvL5js"
    },
    {
      "artist": "Air",
      "name": "Private Hire Igloos with thanks to Air Canada",
      "venue": "Battersea Power Station",
      "city": "London",
      "country": "Great Britain",
      "country_code": "GB",
      "date": "2025-11-16",
      "time": "11:00:00",
      "url": "https://www.universe.com/events/private-hire-igloos-with-thanks-to-air-canada-tickets-V8T3ZB?ref=ticketmaster",
      "source": "Ticketmaster",
      "id": "LvZ18QauHDVGycYZvL5jw"
    },
    {
      "artist": "Air",
      "name": "Private Hire Igloos with thanks to Air Canada",
      "venue": "Battersea Power Station",
      "city": "London",
      "country": "Great Britain",
      "country_code": "GB",
      "date": "2025-11-16",
      "time": "12:00:00",
      "url": "https://www.universe.com/events/private-hire-igloos-with-thanks-to-air-canada-tickets-V8T3ZB?ref=ticketmaster",
      "source": "Ticketmaster",
      "id": "LvZ18QauHDVGycYZvL5jS"
    },
    {
      "artist": "Air",
      "name": "Private Hire Igloos with thanks to Air Canada",
      "venue": "Battersea Power Station",
      "city": "London",
      "country": "Great Britain",
      "country_code": "GB",
      "date": "2025-11-16",
      "time": "13:00:00",
      "url": "https://www.universe.com/events/private-hire-igloos-with-thanks-to-air-canada-tickets-V8T3ZB?ref=ticketmaster",
      "source": "Ticketmaster",
      "id": "LvZ18QauHDVGycYZvL5jV"
    },
    {
      "artist": "Air",
      "name": "Private Hire Igloos with thanks to Air Canada",
      "venue": "Battersea Power Station",
      "city": "London",
      "country": "Great Britain",
      "country_code": "GB",
      "date": "2025-11-16",
      "time": "14:00:00",
      "url": "https://www.universe.com/events/private-hire-igloos-with-thanks-to-air-canada-tickets-V8T3ZB?ref=ticketmaster",
      "source": "Ticketmaster",
      "id": "LvZ18QauHDVGycYZvL5jg"
    }
  ]
}