{
  "timestamp": "2025-11-03T19:55:38.835657",
  "data": {
    "external_urls": {
      "spotify": "https://open.spotify.com/artist/02H68OmCeljWgjoVQVOB1v"
    },
    "followers": {
      "href": null,
      "total": 13568
    },
    "genres": [
      "dark ambient",
      "drone",
      "ambient"
    ],
    "href": "https://api.spotify.com/v1/artists/02H68OmCeljWgjoVQVOB1v",
    "id": "02H68OmCeljWgjoVQVOB1v",
    "images": [
      {
        "url": "https://i.scdn.co/image/b353a6788160b628c0d7e5829fa688aa43044e43",
        "height": 750,
        "width": 1000
      },
      {
        "url": "https://i.scdn.co/image/90924f9104f2fd5737a71677bdc7f53ceac39a83",
        "height": 480,
        "width": 640
      },
      {
        "url": "https://i.scdn.co/image/a19a01d19d3994a2a6abed206236bc4524f20f56",
        "height": 150,
        "width": 200
      },
      {
        "url": "https://i.scdn.co/image/9382120ed1234be0cdc038921faeb94c2ae8d931",
        "height": 48,
        "width": 64
      }
    ],
    "name": "Thomas Köner",
    "popularity": 21,
    "type": "artist",
    "uri": "spotify:artist:02H68OmCeljWgjoVQVOB1v"
  }
}