{
  "timestamp": "2025-08-25T08:51:40.021597",
  "data": [
    {
      "artist": "Kessoncoda",
      "artist_name": "Kessoncoda",
      "name": "Kessoncoda Concert (5uJR7BHe)",
      "venue": "Venue information not available",
      "city": "Location not available",
      "country": "",
      "date": "",
      "time": "",
      "url": "https://open.spotify.com/concert/5uJR7BHeCEBtGYSGlXR8b9",
      "source": "Spotify"
    },
    {
      "artist": "Kessoncoda",
      "artist_name": "Kessoncoda",
      "name": "Kessoncoda Concert (3K1AAObV)",
      "venue": "Venue information not available",
      "city": "Location not available",
      "country": "",
      "date": "",
      "time": "",
      "url": "https://open.spotify.com/concert/3K1AAObVCDB1y34RbiD3pp",
      "source": "Spotify"
    }
  ]
}