{
  "timestamp": "2025-11-03T19:59:51.115600",
  "data": {
    "external_urls": {
      "spotify": "https://open.spotify.com/artist/4lxfqrEsLX6N1N4OCSkILp"
    },
    "followers": {
      "href": null,
      "total": 7352358
    },
    "genres": [
      "soft rock"
    ],
    "href": "https://api.spotify.com/v1/artists/4lxfqrEsLX6N1N4OCSkILp",
    "id": "4lxfqrEsLX6N1N4OCSkILp",
    "images": [
      {
        "url": "https://i.scdn.co/image/ab6761610000e5ebd4e38c4e3e5c82774740e28d",
        "height": 640,
        "width": 640
      },
      {
        "url": "https://i.scdn.co/image/ab67616100005174d4e38c4e3e5c82774740e28d",
        "height": 320,
        "width": 320
      },
      {
        "url": "https://i.scdn.co/image/ab6761610000f178d4e38c4e3e5c82774740e28d",
        "height": 160,
        "width": 160
      }
    ],
    "name": "Phil Collins",
    "popularity": 76,
    "type": "artist",
    "uri": "spotify:artist:4lxfqrEsLX6N1N4OCSkILp"
  }
}