{
  "timestamp": "2025-11-03T20:02:04.128508",
  "data": {
    "external_urls": {
      "spotify": "https://open.spotify.com/artist/20zk0q0gvO55fx1yapc3A0"
    },
    "followers": {
      "href": null,
      "total": 2515
    },
    "genres": [
      "idm",
      "acid house"
    ],
    "href": "https://api.spotify.com/v1/artists/20zk0q0gvO55fx1yapc3A0",
    "id": "20zk0q0gvO55fx1yapc3A0",
    "images": [
      {
        "url": "https://i.scdn.co/image/ab6761610000e5ebdc23df16199c622d97ed1ad8",
        "height": 640,
        "width": 640
      },
      {
        "url": "https://i.scdn.co/image/ab67616100005174dc23df16199c622d97ed1ad8",
        "height": 320,
        "width": 320
      },
      {
        "url": "https://i.scdn.co/image/ab6761610000f178dc23df16199c622d97ed1ad8",
        "height": 160,
        "width": 160
      }
    ],
    "name": "Automatic Tasty",
    "popularity": 5,
    "type": "artist",
    "uri": "spotify:artist:20zk0q0gvO55fx1yapc3A0"
  }
}