{
  "timestamp": "2025-11-03T19:50:15.798292",
  "data": {
    "external_urls": {
      "spotify": "https://open.spotify.com/artist/05jTc62MsTqeytsOkUuka1"
    },
    "followers": {
      "href": null,
      "total": 560
    },
    "genres": [
      "stoner rock"
    ],
    "href": "https://api.spotify.com/v1/artists/05jTc62MsTqeytsOkUuka1",
    "id": "05jTc62MsTqeytsOkUuka1",
    "images": [
      {
        "url": "https://i.scdn.co/image/ab6761610000e5ebdbf089b1383d97e0381dca18",
        "height": 640,
        "width": 640
      },
      {
        "url": "https://i.scdn.co/image/ab67616100005174dbf089b1383d97e0381dca18",
        "height": 320,
        "width": 320
      },
      {
        "url": "https://i.scdn.co/image/ab6761610000f178dbf089b1383d97e0381dca18",
        "height": 160,
        "width": 160
      }
    ],
    "name": "Cosmic Mints",
    "popularity": 2,
    "type": "artist",
    "uri": "spotify:artist:05jTc62MsTqeytsOkUuka1"
  }
}